{
  "diary_id": "王恩茂日记",
  "diary_name": "《王恩茂日记》——红军长征到“七七“事变前夕",
  "char_count": 36883,
  "intro": "",
  "entries": [
    {
      "date_raw": "11 月 5 日",
      "year": 1927,
      "month": 11,
      "day": 5,
      "text": "6时出发，下个4时到沙坪宿营。\n\n1 1 月 6 日\n到达傍湖。该地是红军二军团经常行动的地方，群众 最 好 。\n\n1 1 月 7 日\n前卫部队攻克永顺城，缴获枪支数十支、电话机 及军用品甚多。我们于午时进城。\n\n1 1 月 1 2 日\n8、9、10、11、12这五天，均在水顺城休息。\n\n1 1 月 1 3 日\n陈渠珍准备了10个团的白军向我们进攻。我们为了战略关系，在野外战中消灭敌人，即退出永顺城，到颗沙宿营。\n\n1 1 月 1 4 日\n本来向塔卧前进，因准备与敌人决战，即到官仓坪宿 营。刚到房子里吃完饭后，准备睡的时候，有的睡了，又连 夜开到龙家寨，不久即天亮。\n\n1 1 月 1 5 日\n上午到下午5时在龙家寨附近休息。吃完晚饭后，我 军警戒部队与敌接触。军团直属部队即向沙门村前进，下 午8时到达该地宿营。\n\n1 1 月 1 6 日\n凌晨3时，吃完早饭等天亮，准备打仗。开到毛拔煮 中午饭吃。下午1时，向官坝前进，未至该地而在离官坝10里的地方宿营。是日，我军与敌人-陈渠珍部下的周矮子（周燮卿）约10团之众决战，结果全部敌人被击溃，俘虏和缴获人、枪各千余、无线电台二部、参谋长一人。\n\n1 1 月 1 7 日\n我们战斗部队乘胜追击，收回永顺城，俘虏和缴获人、枪各200余。是日，我因做新同志工作未赶到永顺城， 而在龙家寨宿营。\n\n1 1 月 1 8 日\n由龙家寨到永顺城。\n\n1 1 月 1 9 日\n在永顺休息。下午4时，开祝捷大会，有贺、肖、王（贺龙、肖克、王震）等首长演说，继有六七名新同志讲话，痛说他们在白军里 的痛苦和国民党的罪恶。\n\n1 1 月 2 0 日\n本来决定到达王村，因路远天下雨不好走，即在离干 村40里之洼溪宿营。\n\n1 1 月 2 1 日\n到达王村宿营。\n\n1 1 月 2 2 日\n到松柏场。\n\n1 1 月 2 3 日\n到指坊中心娅。\n\n1 1 月 2 4 日\n命令是前进到四都坪待命行动，后改变攻大庸， 前卫到四都坪打转向大庸前进，至下午2时半攻克大庸， 打败朱疤子（朱华生）。\n\n1 1 月 2 6 日\n25、26日均在大庸城内休息。\n\n1 1 月 2 7 日\n到省委（中共湘鄂川黔省委）工作。\n\n1 1 月 2 8 日\n仍在大庸城内休息。\n\n1 1 月 2 9 日\n省委为着开展大庸城近郊工作，于下午2时迁移于丁家庸。\n\n11 月 3 0 日\n参加政治部会议，讨论白龙安、毛坪、丁家庸等地工 作。\n\n1 2 月 8 日\n1 日至8日均在毛坪、吴家坪、木纳里乡帮助工作，建立政权。\n\n1 2 月 9 日\n省委为着开展湘鄂川黔苏区基本区的工作，决定移  向永顺塔卧办公。上午9时出发，下午4时到达温场宿营。\n\n1 2 月 1 0 日\n由温场出发，下午5时到达塔卧。\n\n1 2 月 1 6 日\n我军东进出击。省委作出开辟根据地的决议。\n\n1 2 月 1 7 日\n我军占领桃源县城。\n\n1 2 月 1 8 日\n我军围攻常德。\n\n1 2 月 1 9 日\n攻打常德不下。\n\n1 2 月 2 0 日\n敌援兵至，我军撤围，退回桃源一带休整。\n\n1 2 月 2 1 日\n我军在桃源地区打土豪。\n\n1 2 月 2 2 日\n省委与军区发布关于游击队中党的工作的指示。\n\n1 2 月 2 4 日\n我军撤出常、桃地区，挺进慈利。省委调整行政区域，永顺县划为永保、郭亮两个县。\n\n1 2 月 2 6 日\n我军与敌接战，进攻和占领慈利县城。\n\n1 2 月 3 0 日\n我军退出慈利县城。\n\n1 2 月 3 1 日\n我军西返大庸、永顺休整，结束湘西攻势。",
      "weather": "",
      "char_count": 1484,
      "diary_id": "王恩茂日记",
      "diary_name": "《王恩茂日记》——红军长征到“七七“事变前夕",
      "diary_index": 1
    },
    {
      "date_raw": "11 月 5 日",
      "year": 1935,
      "month": 11,
      "day": 5,
      "text": "6时出发，下个4时到沙坪宿营。\n\n1 1 月 6 日\n到达傍湖。该地是红军二军团经常行动的地方，群众 最 好 。\n\n1 1 月 7 日\n前卫部队攻克永顺城，缴获枪支数十支、电话机 及军用品甚多。我们于午时进城。\n\n1 1 月 1 2 日\n8、9、10、11、12这五天，均在水顺城休息。\n\n1 1 月 1 3 日\n陈渠珍准备了10个团的白军向我们进攻。我们为了战略关系，在野外战中消灭敌人，即退出永顺城，到颗沙宿营。\n\n1 1 月 1 4 日\n本来向塔卧前进，因准备与敌人决战，即到官仓坪宿 营。刚到房子里吃完饭后，准备睡的时候，有的睡了，又连 夜开到龙家寨，不久即天亮。\n\n1 1 月 1 5 日\n上午到下午5时在龙家寨附近休息。吃完晚饭后，我 军警戒部队与敌接触。军团直属部队即向沙门村前进，下 午8时到达该地宿营。\n\n1 1 月 1 6 日\n凌晨3时，吃完早饭等天亮，准备打仗。开到毛拔煮 中午饭吃。下午1时，向官坝前进，未至该地而在离官坝10里的地方宿营。是日，我军与敌人-陈渠珍部下的周矮子（周燮卿）约10团之众决战，结果全部敌人被击溃，俘虏和缴获人、枪各千余、无线电台二部、参谋长一人。\n\n1 1 月 1 7 日\n我们战斗部队乘胜追击，收回永顺城，俘虏和缴获人、枪各200余。是日，我因做新同志工作未赶到永顺城， 而在龙家寨宿营。\n\n1 1 月 1 8 日\n由龙家寨到永顺城。\n\n1 1 月 1 9 日\n在永顺休息。下午4时，开祝捷大会，有贺、肖、王（贺龙、肖克、王震）等首长演说，继有六七名新同志讲话，痛说他们在白军里 的痛苦和国民党的罪恶。\n\n1 1 月 2 0 日\n本来决定到达王村，因路远天下雨不好走，即在离干 村40里之洼溪宿营。\n\n1 1 月 2 1 日\n到达王村宿营。\n\n1 1 月 2 2 日\n到松柏场。\n\n1 1 月 2 3 日\n到指坊中心娅。\n\n1 1 月 2 4 日\n命令是前进到四都坪待命行动，后改变攻大庸， 前卫到四都坪打转向大庸前进，至下午2时半攻克大庸， 打败朱疤子（朱华生）。\n\n1 1 月 2 6 日\n25、26日均在大庸城内休息。\n\n1 1 月 2 7 日\n到省委（中共湘鄂川黔省委）工作。\n\n1 1 月 2 8 日\n仍在大庸城内休息。\n\n1 1 月 2 9 日\n省委为着开展大庸城近郊工作，于下午2时迁移于丁家庸。\n\n11 月 3 0 日\n参加政治部会议，讨论白龙安、毛坪、丁家庸等地工 作。\n\n1 2 月 8 日\n1 日至8日均在毛坪、吴家坪、木纳里乡帮助工作，建立政权。\n\n1 2 月 9 日\n省委为着开展湘鄂川黔苏区基本区的工作，决定移  向永顺塔卧办公。上午9时出发，下午4时到达温场宿营。\n\n1 2 月 1 0 日\n由温场出发，下午5时到达塔卧。\n\n1 2 月 1 6 日\n我军东进出击。省委作出开辟根据地的决议。\n\n1 2 月 1 7 日\n我军占领桃源县城。\n\n1 2 月 1 8 日\n我军围攻常德。\n\n1 2 月 1 9 日\n攻打常德不下。\n\n1 2 月 2 0 日\n敌援兵至，我军撤围，退回桃源一带休整。\n\n1 2 月 2 1 日\n我军在桃源地区打土豪。\n\n1 2 月 2 2 日\n省委与军区发布关于游击队中党的工作的指示。\n\n1 2 月 2 4 日\n我军撤出常、桃地区，挺进慈利。省委调整行政区域，永顺县划为永保、郭亮两个县。\n\n1 2 月 2 6 日\n我军与敌接战，进攻和占领慈利县城。\n\n1 2 月 3 0 日\n我军退出慈利县城。\n\n1 2 月 3 1 日\n我军西返大庸、永顺休整，结束湘西攻势。",
      "weather": "",
      "char_count": 1484,
      "diary_id": "王恩茂日记",
      "diary_name": "《王恩茂日记》——红军长征到“七七“事变前夕",
      "diary_index": 1
    },
    {
      "date_raw": "1 月 4 日",
      "year": 1935,
      "month": 1,
      "day": 4,
      "text": "湘 鄂J川!黔省委发出战争动员，印发《粉碎敌人进攻， 保卫新苏区的宜言》。",
      "weather": "",
      "char_count": 37,
      "diary_id": "王恩茂日记",
      "diary_name": "《王恩茂日记》——红军长征到“七七“事变前夕",
      "diary_index": 1
    },
    {
      "date_raw": "1 月 6 日",
      "year": 1935,
      "month": 1,
      "day": 6,
      "text": "任弼时书记在省委作演说。\n\n1 月 1 1 日\n首长开会制定作战计划，电报请示中央军委朱德主席。\n\n1 月 2 7 日\n省委在大庸丁家溶召开会议，对夏曦错误（夏曦同志在湘鄂西根据地建设、“肃反”、建军和党 建等方面的错误）进行批评。\n\n1 月 2 8 日\n省委作出关于土地问题的决定。\n\n1 月 2 9 日\n省委指示：筹足战争经费，收集粮食，反对贪污浪费。",
      "weather": "",
      "char_count": 178,
      "diary_id": "王恩茂日记",
      "diary_name": "《王恩茂日记》——红军长征到“七七“事变前夕",
      "diary_index": 1
    },
    {
      "date_raw": "2 月 1 日",
      "year": 1935,
      "month": 2,
      "day": 1,
      "text": "中央白贵州遵义来电：指示作战行动方针。电令组织军事委员会，贺(龙)、任(弼时)、关(向应)、肖(克)、 王(震)为委员，贺任主席。",
      "weather": "",
      "char_count": 65,
      "diary_id": "王恩茂日记",
      "diary_name": "《王恩茂日记》——红军长征到“七七“事变前夕",
      "diary_index": 1
    },
    {
      "date_raw": "2 月 8 日",
      "year": 1935,
      "month": 2,
      "day": 8,
      "text": "在溪口开始反“围剿”战斗。\n\n2 月 2 9 日\n省委发出扩红指示，征集新兵。\n\n3 月 1 0 日\n征兵开始。\n\n3 月 1 3 日\n敌人由王村向永顺方向进攻。\n\n3 月 1 4 日\n我军在高梁坪与敌激战。\n\n3 月 1 5 日\n敌人占领大庸县城。\n\n3 月 2 0 日\n我军在后坪设伏，敌未来。\n\n3 月 2 1 日\n下雨天寒。我军撤回10里休息。敌人先期占领鸡公垭高地，我与敌争夺激战，撤回。\n\n3 月 2 2 日\n任弼时代表省委电请中央，提出转移。\n\n3 月 3 1 日\n中央来电，谈夏曦之事。",
      "weather": "",
      "char_count": 251,
      "diary_id": "王恩茂日记",
      "diary_name": "《王恩茂日记》——红军长征到“七七“事变前夕",
      "diary_index": 1
    },
    {
      "date_raw": "4 月 7 日",
      "year": 1935,
      "month": 4,
      "day": 7,
      "text": "敌人受了溪口、高梁坪、石坪等战争的打击，同时我 们没有大量消火敌人，敌人正向我们基本苏区前进。我们为了在野外运动战当中整师地消灭敌人，粉碎敌人大举进攻，故于是日离开塔卧，到龙家寨之碑立坪乡办公。",
      "weather": "",
      "char_count": 97,
      "diary_id": "王恩茂日记",
      "diary_name": "《王恩茂日记》——红军长征到“七七“事变前夕",
      "diary_index": 1
    },
    {
      "date_raw": "4 月 8 日",
      "year": 1935,
      "month": 4,
      "day": 8,
      "text": "从1934年12月10日起至1935年4月7日止，将近四个月，均在塔卧。",
      "weather": "",
      "char_count": 36,
      "diary_id": "王恩茂日记",
      "diary_name": "《王恩茂日记》——红军长征到“七七“事变前夕",
      "diary_index": 1
    },
    {
      "date_raw": "4 月 9 日",
      "year": 1935,
      "month": 4,
      "day": 9,
      "text": "8、9日均在碑立坪。9日下午随工作团到省革委会宿营。\n\n4 月 1 0 日\n5时出发，前进到万民岗，再走15旦到新街，因陈家河战斗，倒转儿里于长棠坪宿营。\n\n4 月 1 1 日\n从长棠坪出发到简家坡，因陈家河战斗胜利，消灭敌 人二团，我军乘胜追击，于是政治机关亦即星夜赶到仓官 峪宿营。\n\n4 月 1 2 日\n下午3时到陈家河二军团政治部。\n\n4 月 1 3 日\n追击陈耀汉敌至桃子溪，完全打坍敌人四团，缴 获枪支2000余，俘虏近千名。\n\n4 月 1 4 日\n继续追击敌人10余里后，转回泥湖塔宿营。\n\n4 月 1 5 日\n进桑植县城。\n\n4 月 1 6 日\n在桑植城外开祝捷大会。\n\n4 月 1 8 日\n17、18日仍在桑植城。\n\n4 月 1 9 日\n由桑植城到官坝。\n\n\n4 月 2 0 日\n由官坝出发，准备消灭茅坝的敌人，因敌登高山未攻 击，即从马迹凹回到寥家村宿营。\n\n\n4 月 2 3 日\n21、22、23日均在寥家村休息。\n\n\n4 月 2 4 日\n到南岔。\n\n\n4 月 2 5 日\n由南岔到桑植城、捌赖铺、东旺坪至翼家桥宿营，共走 7 5 里 。\n\n\n4 月 2 6 日\n到江垭，保安团在对河打枪。\n\n\n4 月 2 7 日\n在汇垭休息，至下个4时出发到象耳桥。",
      "weather": "",
      "char_count": 537,
      "diary_id": "王恩茂日记",
      "diary_name": "《王恩茂日记》——红军长征到“七七“事变前夕",
      "diary_index": 1
    },
    {
      "date_raw": "4 月 30 日",
      "year": 1935,
      "month": 4,
      "day": 30,
      "text": "28、29、30日三天均在象耳桥休息。",
      "weather": "",
      "char_count": 19,
      "diary_id": "王恩茂日记",
      "diary_name": "《王恩茂日记》——红军长征到“七七“事变前夕",
      "diary_index": 1
    },
    {
      "date_raw": "5 月 1 日",
      "year": 1935,
      "month": 5,
      "day": 1,
      "text": "因敌机4月30日在象耳桥轰炸：为隐蔽敌机起见，故移至唐家峪。",
      "weather": "",
      "char_count": 30,
      "diary_id": "王恩茂日记",
      "diary_name": "《王恩茂日记》——红军长征到“七七“事变前夕",
      "diary_index": 1
    },
    {
      "date_raw": "5 月 2 日",
      "year": 1935,
      "month": 5,
      "day": 2,
      "text": "仍在唐家峪。",
      "weather": "",
      "char_count": 6,
      "diary_id": "王恩茂日记",
      "diary_name": "《王恩茂日记》——红军长征到“七七“事变前夕",
      "diary_index": 1
    },
    {
      "date_raw": "5 月 3 日",
      "year": 1935,
      "month": 5,
      "day": 3,
      "text": "下午4时半出发，转至江垭。",
      "weather": "",
      "char_count": 13,
      "diary_id": "王恩茂日记",
      "diary_name": "《王恩茂日记》——红军长征到“七七“事变前夕",
      "diary_index": 1
    },
    {
      "date_raw": "5 月 4 日",
      "year": 1935,
      "month": 5,
      "day": 4,
      "text": "至叶家桥。",
      "weather": "",
      "char_count": 5,
      "diary_id": "王恩茂日记",
      "diary_name": "《王恩茂日记》——红军长征到“七七“事变前夕",
      "diary_index": 1
    },
    {
      "date_raw": "5 月 5 日",
      "year": 1935,
      "month": 5,
      "day": 5,
      "text": "至双溪河市区街上。",
      "weather": "",
      "char_count": 9,
      "diary_id": "王恩茂日记",
      "diary_name": "《王恩茂日记》——红军长征到“七七“事变前夕",
      "diary_index": 1
    },
    {
      "date_raw": "5 月 6 日",
      "year": 1935,
      "month": 5,
      "day": 6,
      "text": "从双溪河出发，经过桑植城至泥湖塔，随张主任转来桑植城省委。",
      "weather": "",
      "char_count": 29,
      "diary_id": "王恩茂日记",
      "diary_name": "《王恩茂日记》——红军长征到“七七“事变前夕",
      "diary_index": 1
    },
    {
      "date_raw": "5 月 7 日",
      "year": 1935,
      "month": 5,
      "day": 7,
      "text": "检查桑植独立营党的工作，开全营党、团员大会。",
      "weather": "",
      "char_count": 22,
      "diary_id": "王恩茂日记",
      "diary_name": "《王恩茂日记》——红军长征到“七七“事变前夕",
      "diary_index": 1
    },
    {
      "date_raw": "5 月 8 日",
      "year": 1935,
      "month": 5,
      "day": 8,
      "text": "参加修械处被服厂工人大会。工人节省红五月三分 之一的工资，支援战争。",
      "weather": "",
      "char_count": 34,
      "diary_id": "王恩茂日记",
      "diary_name": "《王恩茂日记》——红军长征到“七七“事变前夕",
      "diary_index": 1
    },
    {
      "date_raw": "5 月 9 日",
      "year": 1935,
      "month": 5,
      "day": 9,
      "text": "检查城市区委工作，参加他们的常委会议。\n\n\n5 月 1 0 日\n写《为消灭地主武装告桑植工农群众》。\n\n5 月 1 1 日\n写《红五月工作给各级党组织的指示信》,及修改《桑 植军事部红五月计划》。",
      "weather": "",
      "char_count": 98,
      "diary_id": "王恩茂日记",
      "diary_name": "《王恩茂日记》——红军长征到“七七“事变前夕",
      "diary_index": 1
    },
    {
      "date_raw": "6 月 8 日",
      "year": 1935,
      "month": 6,
      "day": 8,
      "text": "",
      "weather": "",
      "char_count": 0,
      "diary_id": "王恩茂日记",
      "diary_name": "《王恩茂日记》——红军长征到“七七“事变前夕",
      "diary_index": 1
    },
    {
      "date_raw": "5月12日至6月8口均在桑植城。",
      "year": 1935,
      "month": 5,
      "day": 12,
      "text": "",
      "weather": "",
      "char_count": 0,
      "diary_id": "王恩茂日记",
      "diary_name": "《王恩茂日记》——红军长征到“七七“事变前夕",
      "diary_index": 1
    },
    {
      "date_raw": "6 月 9 日",
      "year": 1935,
      "month": 6,
      "day": 9,
      "text": "因江垭、塔卧等地敌人企图大举进攻桑植城，主力红军为消火主要方面的敌人，在宣恩等地活动，离桑植  太远，桑植城有被敌人占领可能，所以，省一级机关及县、 区、乡工作人员加入游击队的一律开至洪家关。\n\n6 月 1 0 日\n在洪家关休息。\n\n\n6 月 1 1 日\n由洪家关出发，到陈家河。本来到仓官峪宿营，因该 处驻了医院，驻不下人。\n\n6 月 1 2 日\n到上河溪。前方来电：击溃敌四十—师全部、四十八 师大部。\n\n\n6 月 1 3 日\n到龙山县之半寨，离龙山60余里。\n\n6 月 1 4 日\n在半寨休息。下午开祝捷大会，庆祝二、六军团伟大 胜利，庆祝中央野战军与红四方面军会合17 的胜利，庆 祝桑植团成立。\n\n6 月 1 5 日\n仍在半寨休息。前方捷报，活捉敌师长张振汉〔2〕,俘 敌2000余人，缴获无线电台两部、枪2000余支，还包围敌 四团正在消灭中。\n\n6 月 1 6 日\n又在半寨休息。\n\n\n6 月 1 7 日\n到 李 家 河 。\n\n\n6 月 1 8 日\n在李家河休息。\n\n\n6 月 1 9 日\n下午由李家河移到李家河的街口，前进一二里。\n\n\n6 月 2 0 日\n在李家河开祝捷大会：庆祝忠堡战斗的胜利。\n\n\n6 月 2 1 日\n到兴隆界。\n\n\n6 月 2 3 日\n22、23日在兴隆界休息。\n\n\n7 月 1 8 日",
      "weather": "",
      "char_count": 562,
      "diary_id": "王恩茂日记",
      "diary_name": "《王恩茂日记》——红军长征到“七七“事变前夕",
      "diary_index": 1
    },
    {
      "date_raw": "6月24日到7月18日仍驻兴隆界，",
      "year": 1935,
      "month": 6,
      "day": 24,
      "text": "7 月 2 8 日\n19日至28日均在岩山坪。\n\n\n7 月 2 9 日\n上午11时移往茨岩塘。\n\n\n8 月 2 2 日\n7 月 3C日至8月22日都驻在茨岩塘，\n\n\n8 月 2 3 日\n凌晨2时半，向桑植前进，抵上河溪宿营。",
      "weather": "",
      "char_count": 112,
      "diary_id": "王恩茂日记",
      "diary_name": "《王恩茂日记》——红军长征到“七七“事变前夕",
      "diary_index": 1
    },
    {
      "date_raw": "8 月 24 日",
      "year": 1935,
      "month": 8,
      "day": 24,
      "text": "抵两河口宿营。在将到陈家河时，途遇敌机两架，投\n弹四颗。\n\n\n8 月 2 5 日\n上午11时到达桑植城内。\n\n\n1 1 月 1 8 日",
      "weather": "",
      "char_count": 67,
      "diary_id": "王恩茂日记",
      "diary_name": "《王恩茂日记》——红军长征到“七七“事变前夕",
      "diary_index": 1
    },
    {
      "date_raw": "8月26日至11月18日均在桑植城。",
      "year": 1935,
      "month": 8,
      "day": 26,
      "text": "11 月 1 9 日\n离开桑植城到达大庸之三家亭(离教子垭一里),开 始离开了湘鄂川黔苏区。\n\n\n1 1 月 2 0 日\n原决定到达大庸之张家湾宿营，以便清早渡澧水，全 部突破敌人封锁线。因路程太远，是日未到宿营目的地， 即在火烧桥宿营。\n\n\n1 1 月 2 1 日\n清早到达张家湾并前进到兴隆界，准备渡澧水，因浮 桥未搭好，即在兴隆界柑子树林中隐蔽，以避敌机。12点 半钟敌机来了，但未发现目标，没有丢炸弹。下午2点钟 敌机复来，此时浮桥已搭好，有一部分人过桥，因敌机发现目标，投弹十几颗，玉珠（周玉珠）同志中弹牺牲。2点半钟敌 机又来，投弹十颗。3点许敌机再来，丢弹八颗。此时我们 已渡过澧水了。下午5点钟，我们到大庸之松塔宿营。\n\n\n1 1 月 2 2 日\n到达沅陵之桥头孙家坪宿营。\n\n\n1 1 月 2 3 日\n天未亮即出发，至天黑7时半，才到沅陵之洞庭溪 (即沅江边)宿营。\n\n1 1 月 2 4 日\n早渡沅江，前进50余里，到凉水坪宿营。\n\n\n1 1 月 2 5 日\n原决定到杨家坪宿营，因路途太远，未抵该地，而在 土地坳宿营。\n\n\n1 1 月 2 6 日\n从土地坳出发，到箐箕湾上汽车路，到船溪驿宿营。\n\n\n1 1 月 2 7 日\n从船溪驿出发，走40里汽车路，上午11时进辰溪 县。\n\n1 1 月 3 0 日\n28日到30日均在辰溪城休息。\n\n\n1 2 月 1 日\n从辰溪城出发，到倒阁台宿营，离溆浦城30多里。\n\n1 2 月 2 日\n到达溆浦城 。\n\n\n1 2 月 3 日\n在淑浦城休息。\n\n\n1 2 月 4 日\n由于我们胜利的行动，已经调动了敌人。是日，准备 消灭蒋敌主力。从淑浦城到达胡家坪，离溆浦城60里。\n\n1 2 月 5 日\n由胡家坪到达江溪。\n\n\n1 2 月 6 日\n准备战斗，决定经大水田消灭敌之运动纵队，不意敌 人先期通过了大水田到马路口，我军即在大水田宿营，未 进行战斗。\n\n1 2 月 7 日\n决定追击马路口蒋敌主力部队 —樊纵队,因敌 登好了阵地，故另寻找新的机动，打转到黄竹田宿营。\n\n1 2 月 8 日\n山黄竹田到达王稠宿营。\n\n\n1 2 月 9 日\n到潭家湾。\n\n\n1 2 月 1 0 日\n到祖师殿之溜溪。\n\n\n1 2 月 1 1 日\n上午在溜溪休息，下午1时出发，至4时到大址坊宿 营。\n\n1 2 月 1 2 日\n到二团宿营。经过路途都是冰山冰地，很难行走。\n\n1 2 月 1 3 日\n落大雪。经过分水界、黄土坎一带山地，树木、房屋都被雪掩蔽，路途都结成了冰，行军很滑，跌跤的不少，到达 金鸡垅宿营。\n\n1 2 月 1 4 日\n天亮吃饭，等待命令出发，等了约五个小时，至11时 出发，下午5时半到达黄金井管辖的区域。\n\n12月15 B\n8时出发，下午1时到达隆回司。\n\n1 2 月 1 6 日\n上午在隆回司休息，下午2时半出发，倒转五箩宿 营。\n\n1 2 月 1 7 日\n在五箩休息。战斗部队出发与敌人决战。\n\n1 2 月 1 8 日\n由五箩出发，经过隆回可、六都寨，沿途备受群众欢迎，特别是六都寨街上，打鞭炮，写“欢迎”旗子和标语口 号，如“工农红军是为工农群众解除痛苦的军队”、“苏维 埃政府万上岁”等字样。下个3时半到达朝阳铺宿营，\n\n1 2 月 1 9 日\n本来到武冈之洞口宿营，结果只到离洞口20里 之清和桥宿营。\n\n1 2 月 2 0 日\n从清和桥出发，走了六七里，即走汽车路到洞口，休 息二三小时渡资水，赶到花园宿营，走三四里夜路。\n\n\n1 2 月 2 1 日\n在花园休息。六军团从花园经过，敌机米了一次，未 丢炸弹于花园，而丢在较远的地方。\n\n1 2 月 2 2 日\n从花园出发，攻击瓦屋塘之陶纵队,至牛栏冲，即 与敌接触，囚敌已登好阵地，未与敌决战而退回黄土坎宿 营(武冈)。\n\n\n1 2 月 2 3 日\n从黄土坎到武阳(武冈县管辖的)宿营。\n\n\n1 2 月 2 4 日\n下大雪。6点半钟出发，等了三四点钟，到12点钟上 下才动身，走到凉水井即天黑了，摸了20多里夜路，才渡 河至竹舟江(绥宁管辖的地方)。\n\n1 2 月 2 5 日\n经过金鱼口、岩山脚、枰江到达王家坪宿营(会同边地)。\n\n\n1 2 月 2 6 日\n下大雪。经过团河、小江，盛储，到达帅溪宿营。\n\n\n1 2 月 2 7 日\n从帅溪到堡子脚，休息三四点钟，到达兵见宿营。",
      "weather": "",
      "char_count": 1800,
      "diary_id": "王恩茂日记",
      "diary_name": "《王恩茂日记》——红军长征到“七七“事变前夕",
      "diary_index": 1
    },
    {
      "date_raw": "12 月 28 日",
      "year": 1935,
      "month": 12,
      "day": 28,
      "text": "向江西街前进，北渡沅江，到达朱家坊宿营(黔阳辖 地 ) 。\n\n1 2 月 2 9 日\n7时出发，11时到达原神场休息大兰大。\n\n\n1 2 月 3 0 日\n6时半出发，下午3时许到达麻堰场宿营，\n\n\n1 2 月 3 1 日\n7时出发，走了四五里路即走汽车路，到达冷水铺之哀 冲 。",
      "weather": "",
      "char_count": 139,
      "diary_id": "王恩茂日记",
      "diary_name": "《王恩茂日记》——红军长征到“七七“事变前夕",
      "diary_index": 1
    },
    {
      "date_raw": "12 月 28 日",
      "year": 1936,
      "month": 12,
      "day": 28,
      "text": "向江西街前进，北渡沅江，到达朱家坊宿营(黔阳辖 地 ) 。\n\n1 2 月 2 9 日\n7时出发，11时到达原神场休息大兰大。\n\n\n1 2 月 3 0 日\n6时半出发，下午3时许到达麻堰场宿营，\n\n\n1 2 月 3 1 日\n7时出发，走了四五里路即走汽车路，到达冷水铺之哀 冲 。",
      "weather": "",
      "char_count": 139,
      "diary_id": "王恩茂日记",
      "diary_name": "《王恩茂日记》——红军长征到“七七“事变前夕",
      "diary_index": 1
    },
    {
      "date_raw": "1 月 1 日",
      "year": 1937,
      "month": 1,
      "day": 1,
      "text": "在哀冲(芷江县管的)过年。是口，召开政治干部 会议，解释这次行动的意义和检查政治工作。",
      "weather": "",
      "char_count": 43,
      "diary_id": "王恩茂日记",
      "diary_name": "《王恩茂日记》——红军长征到“七七“事变前夕",
      "diary_index": 1
    },
    {
      "date_raw": "1 月 2 日",
      "year": 1936,
      "month": 1,
      "day": 2,
      "text": "7时半出发，都是走汽车路，到便水渡河，于新店坪、 上坪一线宿营，",
      "weather": "",
      "char_count": 32,
      "diary_id": "王恩茂日记",
      "diary_name": "《王恩茂日记》——红军长征到“七七“事变前夕",
      "diary_index": 1
    },
    {
      "date_raw": "1 月 3 日",
      "year": 1936,
      "month": 1,
      "day": 3,
      "text": "7时出发，又是走汽车路，胜利地到达龙溪口，占领晃 县,",
      "weather": "",
      "char_count": 27,
      "diary_id": "王恩茂日记",
      "diary_name": "《王恩茂日记》——红军长征到“七七“事变前夕",
      "diary_index": 1
    },
    {
      "date_raw": "1 月 4  日",
      "year": 1936,
      "month": 1,
      "day": 4,
      "text": "在龙溪口休息。",
      "weather": "",
      "char_count": 7,
      "diary_id": "王恩茂日记",
      "diary_name": "《王恩茂日记》——红军长征到“七七“事变前夕",
      "diary_index": 1
    },
    {
      "date_raw": "1 月 5 日",
      "year": 1936,
      "month": 1,
      "day": 5,
      "text": "上午8时半出发，去攻击新店坪、上坪一线的敌人。 下午，二、六军团即与敌人接触，4时许增加四师上火线。 是日夜晚，即在狮子岭山脚下宿营。敌我两方战斗部队均  在山上打仗，",
      "weather": "",
      "char_count": 84,
      "diary_id": "王恩茂日记",
      "diary_name": "《王恩茂日记》——红军长征到“七七“事变前夕",
      "diary_index": 1
    },
    {
      "date_raw": "1 月 6 日",
      "year": 1936,
      "month": 1,
      "day": 6,
      "text": "吃完饭即上山。二军团四师及六师一部牵制敌人两 个师，六军团突击敌人一师，准备消灭敌人，与敌决战一 天，下午8时，退到竹黄坪宿营。",
      "weather": "",
      "char_count": 64,
      "diary_id": "王恩茂日记",
      "diary_name": "《王恩茂日记》——红军长征到“七七“事变前夕",
      "diary_index": 1
    },
    {
      "date_raw": "1 月 7 日",
      "year": 1936,
      "month": 1,
      "day": 7,
      "text": "由竹黄平倒回龙溪口，下午5时，由龙溪口到王家溪 宿营，完全走的夜路。",
      "weather": "",
      "char_count": 34,
      "diary_id": "王恩茂日记",
      "diary_name": "《王恩茂日记》——红军长征到“七七“事变前夕",
      "diary_index": 1
    },
    {
      "date_raw": "1 月 8 日",
      "year": 1936,
      "month": 1,
      "day": 8,
      "text": "由王家溪到玉屏之朱家塘宿营。",
      "weather": "",
      "char_count": 14,
      "diary_id": "王恩茂日记",
      "diary_name": "《王恩茂日记》——红军长征到“七七“事变前夕",
      "diary_index": 1
    },
    {
      "date_raw": "1 月 9 日",
      "year": 1936,
      "month": 1,
      "day": 9,
      "text": "由朱家塘到岑巩县1〕之羊研宿营。\n\n\n1 月 1 0 日\n由羊硚出发，走一天山路，本来到平牙宿营，集结待 机，后改变到凯阳塘(仍是岑巩县管的)宿营。\n\n1 月 1 1 日\n上午7时出发，又是走一天山路。路上简直没有什么 民房，到达石阡县之石家湾宿营。该地离石阡城60 里。四师是日已攻克县城，捉获洋人(德国人)一个，得德 国纸洋20余万元。\n\n\n1 月 1 2 日\n上午7时由石家湾出发，下午2时许由石阡东门进 城，到达石阡城之天主堂宿营。\n\n1 月 1 9 日\n13口至19日均在石阡城休息。\n\n1 月 2 0 日\n由石阡出发，当天到白沙宿营。\n\n1 月 2 1 日\n命令上决定到达龙溪宿营，但因冲破敌人河坝场至 龙溪一线堡垒封锁线的关系，故未到达而在渡过河坝这 条河后前进15里之沙坝露营。\n\n1 月 2 2 日\n继续向龙溪前进。因龙溪一带山岭都有碉堡，并有卖 国军廿三师守碉堡，企图阻碍我们的行动，故我们弯了龙 溪，到茅坪哨休息煮饭吃(因昨天半天至今天早晨未吃 饭)。下午4时半出发，到草灰坪宿营。\n\n1 月 2 3 日\n由草灰坪到达猴场宿营。\n\n1 月 2 4 日\n上午10时许，由猴场出发，到达瓮安城。\n\n\n1 月 2 5 日\n由瓮安城出发，到达牛场宿营。\n\n\n1 月 2 6 日\n上午5时出发，准备迎击马场坪的敌人(九十九师之 一团)及增援马场坪的敌人。下午1时进平越二城(前卫 上午7时即进城),击溃守城敌人千余人，连续追击敌人， 缴到枪100余支，连枪10支(内四支白动的)。\n\n1 月 2 7 日\n7时由平越出发，到达大麻窝宿营。该地有一半花 苗。\n\n1 月 2 8 日\n7时由大麻窝出发，下午1时到达龙里县之洗马 河宿营。该地距贵阳90里，因此贵阳之敌异常恐慌。\n\n1 月 2 9 日\n在洗马河休息。\n\n\n1 月 3 0 日\n由洗马河出发，下午4时半到达贵阳之新铺宿营，走 了 8 0 里 。\n\n\n1 月 3 1 日\n由新铺出发至三重堰，截击由贵阳开往扎佐的敌人 汽车两辆，缴到炸弹千余、子弹数十箱，军用品甚多。继续 前进，击溃由贵阳开往扎佐企图阻碍我们西进的保安第 一 、二团，俘虏和缴获人、枪各300余。五师袭击修文城，在途中俘虏和缴获由扎佐溃退的保安团人、枪各30余，乘脸进占修文城，城内保安团纷纷逃窜。",
      "weather": "",
      "char_count": 965,
      "diary_id": "王恩茂日记",
      "diary_name": "《王恩茂日记》——红军长征到“七七“事变前夕",
      "diary_index": 1
    },
    {
      "date_raw": "2 月 1 日",
      "year": 1936,
      "month": 2,
      "day": 1,
      "text": "9时出发至修文城外集合，到11时才走，经过五里： 六师前卫捉获由修文城逃跑的县长。继续前进，顺利地渡 过索桥河，下午6时到达镇西卫宿营。",
      "weather": "",
      "char_count": 68,
      "diary_id": "王恩茂日记",
      "diary_name": "《王恩茂日记》——红军长征到“七七“事变前夕",
      "diary_index": 1
    },
    {
      "date_raw": "2 月 2 日",
      "year": 1936,
      "month": 2,
      "day": 2,
      "text": "在镇西卫休息。",
      "weather": "",
      "char_count": 7,
      "diary_id": "王恩茂日记",
      "diary_name": "《王恩茂日记》——红军长征到“七七“事变前夕",
      "diary_index": 1
    },
    {
      "date_raw": "2 月 3 日",
      "year": 1936,
      "month": 2,
      "day": 3,
      "text": "上个7时由镇西卫出发，12时顺利地渡过鸭池河(即 乌江的上游),下午1时到达烂泥沟宿营。",
      "weather": "",
      "char_count": 44,
      "diary_id": "王恩茂日记",
      "diary_name": "《王恩茂日记》——红军长征到“七七“事变前夕",
      "diary_index": 1
    },
    {
      "date_raw": "2 月 4 日",
      "year": 1936,
      "month": 2,
      "day": 4,
      "text": "进黔西城。",
      "weather": "",
      "char_count": 5,
      "diary_id": "王恩茂日记",
      "diary_name": "《王恩茂日记》——红军长征到“七七“事变前夕",
      "diary_index": 1
    },
    {
      "date_raw": "2 月 5 日",
      "year": 1936,
      "month": 2,
      "day": 5,
      "text": "在黔西城休息。",
      "weather": "",
      "char_count": 7,
      "diary_id": "王恩茂日记",
      "diary_name": "《王恩茂日记》——红军长征到“七七“事变前夕",
      "diary_index": 1
    },
    {
      "date_raw": "2 月 6 日",
      "year": 1936,
      "month": 2,
      "day": 6,
      "text": "由黔西城出发，迎击由遵义开来三重堰、打鼓一线的 敌人——郝梦龄部及五十四师。因敌人未动，故走到 离城20里的地方即打转回城。",
      "weather": "",
      "char_count": 62,
      "diary_id": "王恩茂日记",
      "diary_name": "《王恩茂日记》——红军长征到“七七“事变前夕",
      "diary_index": 1
    },
    {
      "date_raw": "2 月 7 日",
      "year": 1936,
      "month": 2,
      "day": 7,
      "text": "山政治部回省委工作。在黔西城休息。",
      "weather": "",
      "char_count": 17,
      "diary_id": "王恩茂日记",
      "diary_name": "《王恩茂日记》——红军长征到“七七“事变前夕",
      "diary_index": 1
    },
    {
      "date_raw": "2 月 8 日",
      "year": 1936,
      "month": 2,
      "day": 8,
      "text": "7时由黔西出发，下午4时半到达廿荫堂宿营。",
      "weather": "",
      "char_count": 21,
      "diary_id": "王恩茂日记",
      "diary_name": "《王恩茂日记》——红军长征到“七七“事变前夕",
      "diary_index": 1
    },
    {
      "date_raw": "2 月 9 日",
      "year": 1936,
      "month": 2,
      "day": 9,
      "text": "由甘荫堂出发，下午3时到达大定城。\n\n2 月 1 6 日\n从10日至16日均在大定城办公。\n\n\n2 月 1 7 日\n上午7时由大定城出发，到达毕节。",
      "weather": "",
      "char_count": 74,
      "diary_id": "王恩茂日记",
      "diary_name": "《王恩茂日记》——红军长征到“七七“事变前夕",
      "diary_index": 1
    },
    {
      "date_raw": "2月18日",
      "year": 1936,
      "month": 2,
      "day": 18,
      "text": "在毕节城办公。省委开委员会议，讨论中央政治局1 月27日决议。是日，二军团击溃卖国军五十四师，缴获枪 支200余。\n\n2 月 1 9 日\n仍在毕节城，省委机关由毕节民众俱乐部移至西门 办公。六军团击溃敌人十三师出三个团选出的六个精壮  连，缴获步枪300余支、驳壳枪10余支、轻重机关枪9挺。\n\n2 月 2 6 日\n从20日至26日均在毕节城。\n\n\n2 月 2 7 日\n上午5时出发，下午3时到达五股、田坝宿营。\n\n\n2 月 2 8 日\n上午6时出发，下午2时到达阴底、谭官峪宿营。\n\n\n2 月 2 9 日\n上午7时出发，下午6时到达离平山铺10里的地方 宿营。夏主任（夏曦）是日牺牲：",
      "weather": "",
      "char_count": 293,
      "diary_id": "王恩茂日记",
      "diary_name": "《王恩茂日记》——红军长征到“七七“事变前夕",
      "diary_index": 1
    },
    {
      "date_raw": "3 月 1 日",
      "year": 1936,
      "month": 3,
      "day": 1,
      "text": "在平山铺附近的下寨休息。",
      "weather": "",
      "char_count": 12,
      "diary_id": "王恩茂日记",
      "diary_name": "《王恩茂日记》——红军长征到“七七“事变前夕",
      "diary_index": 1
    },
    {
      "date_raw": "3 月 2 日",
      "year": 1936,
      "month": 3,
      "day": 2,
      "text": "仍在下寨休息。",
      "weather": "",
      "char_count": 7,
      "diary_id": "王恩茂日记",
      "diary_name": "《王恩茂日记》——红军长征到“七七“事变前夕",
      "diary_index": 1
    },
    {
      "date_raw": "3 月 3 日",
      "year": 1936,
      "month": 3,
      "day": 3,
      "text": "上午8时出发，下午4时到达七家湾(威宁）宿营。",
      "weather": "",
      "char_count": 23,
      "diary_id": "王恩茂日记",
      "diary_name": "《王恩茂日记》——红军长征到“七七“事变前夕",
      "diary_index": 1
    },
    {
      "date_raw": "3 月 4 日",
      "year": 1936,
      "month": 3,
      "day": 4,
      "text": "上个6时出发，下午5时到达威宁的妈姑宿营，没有 饭吃，只吃点包谷。",
      "weather": "",
      "char_count": 33,
      "diary_id": "王恩茂日记",
      "diary_name": "《王恩茂日记》——红军长征到“七七“事变前夕",
      "diary_index": 1
    },
    {
      "date_raw": "3 月 5 日",
      "year": 1936,
      "month": 3,
      "day": 5,
      "text": "到达小河口宿营。是日落雪，经过山地都已结冰.宿 营地房子很少，没有饭吃，都是吃包谷。",
      "weather": "",
      "char_count": 42,
      "diary_id": "王恩茂日记",
      "diary_name": "《王恩茂日记》——红军长征到“七七“事变前夕",
      "diary_index": 1
    },
    {
      "date_raw": "3 月 6 日",
      "year": 1936,
      "month": 3,
      "day": 6,
      "text": "上4年下雪，下午天晴。到达威宁的可乐之张家沟宿 营。此地房子更少，没有地方睡觉，住在一个小房子里，与 牛栏无异，同时没有饭吃。\n从2月27日起至3月6日止，经过五股、田坝、阴底、 平山铺、七家湾、妈姑、小河口、可乐等地，沿途房子很少， 高山多，平地少，群众生活异常贫苦，住的都是矮茅屋，吃的都是包谷、洋芋、草根，穿的没有一块完全的棉布，盖的 没有棉被而是茅草。",
      "weather": "",
      "char_count": 180,
      "diary_id": "王恩茂日记",
      "diary_name": "《王恩茂日记》——红军长征到“七七“事变前夕",
      "diary_index": 1
    },
    {
      "date_raw": "3 月 7 日",
      "year": 1936,
      "month": 3,
      "day": 7,
      "text": "下大雪，路不好走，天气严寒。上午5时出发，下午4 时到达云南奎香。这是离开贵州，第一次进入云南的天。",
      "weather": "",
      "char_count": 50,
      "diary_id": "王恩茂日记",
      "diary_name": "《王恩茂日记》——红军长征到“七七“事变前夕",
      "diary_index": 1
    },
    {
      "date_raw": "3 月 8 日",
      "year": 1936,
      "month": 3,
      "day": 8,
      "text": "敌樊嵩甫纵队之二十八师到达可乐，准备于是日进 到奎香。我军决定在敌前进到以则河时消灭之，因此全军 团战斗部队与二军团之四师回转于板栗、以则河一线集 结，待机消灭敌人。敌先头部队(一个步兵连、 一个侦察 连)的确来了，我军即全部把它消灭，缴到步枪100余支、 驳壳枪20余支，俘虏数十人。",
      "weather": "",
      "char_count": 143,
      "diary_id": "王恩茂日记",
      "diary_name": "《王恩茂日记》——红军长征到“七七“事变前夕",
      "diary_index": 1
    },
    {
      "date_raw": "3 月 9 日",
      "year": 1936,
      "month": 3,
      "day": 9,
      "text": "在奎香休息。\n\n\n3 月 1 0 日\n由奎香出发到村曰坝，再前进五里宿营。\n\n\n3 月 1 1 日\n上午4时出发，下午3时半到达牛场宿营，走了105 里(牛场即镇雄)第七区巾帼乡。\n\n3 月 1 2 日\n到达西沙沟宿营(离牛场坝15里)。二军团一部击溃 白军十三师万耀煌部，缴获轻重机关枪八九挺。\n\n3 月 1 3 日\n在西沙沟休息半天，下午1 时出发，到达西子脚宿 营 。\n\n3 月 1 4 日\n到达墨车宿营。\n\n\n3 月 1 5 日\n上午7时出发，经过沙坝、议河，下午5时到达青山宿 营。\n\n\n3 月 1 6 日\n上车5时出发，经过板栗等地，到达奎香宿营。\n\n\n3 月 1 7 日\n上午7时30分出发，经过打仗坡等地，到达云贵桥之 大寨宿营。\n\n3 月 1 8 日\n上午5时30分出发，向得胜坡前进，到达离得胜坡 30里的初朵岩宿营。\n\n3 月 1 9 日\n继续向得胜坡前进，经过得胜坡、白布沙，到达丫子 口宿营。此地房子很少，大部分部队露营。同时本日刮大 风，走路尘沙纷起，妨碍呼吸。\n\n3 月 2 0 日\n上午6时出发，经过大寨、河坝、车洛，到达潘家沟宿 营。从青山一带起到潘家沟一带止，走的都是贵州的地 区 。\n\n3 月 2 1 日\n由潘家沟出发，经过韭菜冲等地，到达云南宜威1 的芝加宿营。\n\n\n3 月 2 2 日\n到达观音堂宿营。此地距离宣威城25里。\n\n\n3 月 2 3 日\n在观音堂休息，随时准备战斗。滇敌四团由宣威 城出击，我军将其全部击溃，缴获枪支三四百、轻机枪数 挺。我军继续进攻敌人，因敌孙纵队增援六团，同时准备了阵地，故未取得全部胜利。\n\n3 月 2 4 日\n我军向东南转移寻找新的机动。凌晨4时准备完毕， 集合待命，5时出发，到达宣威城小未宿营。因前头部队运  动不快，沿途休息，以致摸了四五里夜路。\n\n3 月 2 5 日\n上午9时出发，经过支脉等地，到达羊场(赫得冲大 地名)之毛家村(赫得冲小地名)宿营。\n\n3 月 2 6 日\n在毛家村休息，恢复疲劳。\n\n\n3 月 2 7 日\n上午7时出发，经过水坪子，前卫到达西心点与滇敌 两团遭遇，被我前卫击垮，军直即在西心点休息数小时， 继续向兔场前进，到达该地前进二三里的阴坡沟宿营。\n\n3 月 2 8 日\n上午5时出发，向平彝前进，经过白龙洞、后所、 山口，离城(平彝)二三里，望见城内地主武装打枪，因敌  情与我们任务的关系未攻克城，再向东转移，经过东甫到 达孙官坪宿营。本日来飞机两次：第一次我们在后所，丢 了一个炸弹在该地，部队毫无损失；丢了三四个炸弹丁十 七师供给部，打死八九头骡子；丢了二二个炸弹于前卫部 队(十六师)离城二三里的地方，打死几个带花的。第二次 围绕平彝城周围打圈，丢弹五六个，伤亡数名。前卫经过 后所，击溃平彝保安团，缴获枪支20余。五十三团与教导 团到达孙官坪，击溃固守该地之乡兵(乡兵即县长压迫群 众派去当兵的),缴获枪支数支。\n\n3 月 2 9 日\n上午6时出发，经过平彝，到达盘县分界——亦资孔宿营。这天离开了云南。\n\n3 月 3 0 日\n在亦资孔休息。\n\n\n3 月 3 1 日\n向南转移，经过分水岭到贵州盘县下六区(即乐民所)宿营。",
      "weather": "",
      "char_count": 1323,
      "diary_id": "王恩茂日记",
      "diary_name": "《王恩茂日记》——红军长征到“七七“事变前夕",
      "diary_index": 1
    },
    {
      "date_raw": "4 月 1 日",
      "year": 1936,
      "month": 4,
      "day": 1,
      "text": "向西前进，经过水东坪、沙基、清水塘、菁口、划船边， 过铁链木板桥，到达沾益县羊场堰之赫岩宿营。本日 又离开了贵州，进入云南。",
      "weather": "",
      "char_count": 62,
      "diary_id": "王恩茂日记",
      "diary_name": "《王恩茂日记》——红军长征到“七七“事变前夕",
      "diary_index": 1
    },
    {
      "date_raw": "4 月 2 日",
      "year": 1936,
      "month": 4,
      "day": 2,
      "text": "向西南前进，经过老猪街、洛岗、朝阳菁，到达平彝县 之西流水宿营。",
      "weather": "",
      "char_count": 32,
      "diary_id": "王恩茂日记",
      "diary_name": "《王恩茂日记》——红军长征到“七七“事变前夕",
      "diary_index": 1
    },
    {
      "date_raw": "4  月  3  日",
      "year": 1936,
      "month": 4,
      "day": 3,
      "text": "上午5时半出发，经过白石岩、那坡、张官营、三百户 营、马厂、观音洞、西基坟，到达马龙县之火烧菁宿营。 此地离马龙城25里。自经过白石岩、那坡一线高山后，张 官营、三百户营(张官营、三百户营离曲靖县仅20里）即一场平地，很大田坝，群众拥挤在路旁卖东西，表示拥 护红军 . 是日共走了130余里。",
      "weather": "",
      "char_count": 146,
      "diary_id": "王恩茂日记",
      "diary_name": "《王恩茂日记》——红军长征到“七七“事变前夕",
      "diary_index": 1
    },
    {
      "date_raw": "4 月 4 日",
      "year": 1936,
      "month": 4,
      "day": 4,
      "text": "向白塔铺以南前进，经过打架庄(离马龙城仅四五 里)、沧浪坡、黄土坡、白塔铺、缩落村，到达寻甸县之 草海、板桥宿营。此地离寻甸县70里，离昆明200里。是 日敌机共来四次，投弹数十颗，后卫稍受损失。",
      "weather": "",
      "char_count": 98,
      "diary_id": "王恩茂日记",
      "diary_name": "《王恩茂日记》——红军长征到“七七“事变前夕",
      "diary_index": 1
    },
    {
      "date_raw": "4 月 5 日",
      "year": 1936,
      "month": 4,
      "day": 5,
      "text": "向羊街西北前进，经过照火仆、灵神庙、大野、塘梓、 全所、枫阳村、新街、羊街，到达余家屯宿营。此地有较大  的垅亩，人烟比较稠密，离寻甸城50里。是日，敌机连续  来往三四次，拼命寻找我们的目标，但是徒费气力，没有  起到任何作用。",
      "weather": "",
      "char_count": 115,
      "diary_id": "王恩茂日记",
      "diary_name": "《王恩茂日记》——红军长征到“七七“事变前夕",
      "diary_index": 1
    },
    {
      "date_raw": "4 月 6 日",
      "year": 1936,
      "month": 4,
      "day": 6,
      "text": "在余家屯休息，敌机来了三四次，但未找到我们的目 标。",
      "weather": "",
      "char_count": 26,
      "diary_id": "王恩茂日记",
      "diary_name": "《王恩茂日记》——红军长征到“七七“事变前夕",
      "diary_index": 1
    },
    {
      "date_raw": "4 月 7 日",
      "year": 1936,
      "month": 4,
      "day": 7,
      "text": "向可郎前进，经过磨盘寺、三家村、法耳果、余家村、 代家村、木龙马、磨腮村，到达可郎宿营。该地是寻甸县第  八区属地，离昆明120里， 一天可以走到。是日敌机来了  一次，未发现我们部队的目标。",
      "weather": "",
      "char_count": 96,
      "diary_id": "王恩茂日记",
      "diary_name": "《王恩茂日记》——红军长征到“七七“事变前夕",
      "diary_index": 1
    },
    {
      "date_raw": "4 月 8 日",
      "year": 1936,
      "month": 4,
      "day": 8,
      "text": "向款庄前进，准备渡过普渡河。前卫将抵款庄，发现 滇敌约三四个团，企图阻挠我军。我军与滇敌激战数小 时，前后三四次反冲锋，本来将敌全部击溃，缴获甚多，后 因敌机捣乱阵地，未能取得战斗胜利，故未抵款庄和达到 渡河日的，而寻找新的机动，到达寻甸之胡家村宿营。",
      "weather": "",
      "char_count": 126,
      "diary_id": "王恩茂日记",
      "diary_name": "《王恩茂日记》——红军长征到“七七“事变前夕",
      "diary_index": 1
    },
    {
      "date_raw": "4 月 9 日",
      "year": 1936,
      "month": 4,
      "day": 9,
      "text": "凌晨1时出发，到达益南坝的大古村尚未天亮，在该 地休息半天：吃完中午饭后，滇敌追击我们，我军沉着应 战，一面抵抗，一面向可度转移。是日，全军团顺利地到达 可度宿营。\n\n\n4 月 1 0 日\n向南行动。凌晨3时出发，经过可郎、小猴场、茶凹 坡，小新街，到达嵩明县第七区永和乡(羊街)宿营。我 们为了坚决地完成西渡普渡河，故于本日下午9时半出 发，实行夜行军，经过瓦厂、散旦街、平地等地，于11日上 午9时顺利地渡过普渡河，到达富民县之赤就。\n\n4 月 1 1 日\n上午10时至下午均在赤就休息。\n\n\n4 月 1 2 日\n凌晨2时半出发，向罗次县前进，经过者白、乐古 村、大落勉、椒地山、五朵朵及罗次城边，到达下右卫村宿 营。\n\n4 月 1 3 日\n向西前进，经过七排、秧草地，到达戴古老村宿营(该 地是武定属地)。\n\n4 月 1 4 日\n继续向西前进，经过大营哨、草溪井，到达盐兴县 的元永井(即猴井)宿营。前卫部队击溃固守该地的保警  队，缴获步枪30余支，俘虏官兵30余人。\n\n4 月 1 5 日\n向盐兴县城前进，经过小铺子等地，到达盐兴城，击 溃守城的乡兵。这是第一次进云南的县城。\n\n4 月 1 6 日\n向牟定县前进，经过琅井、工家村、杨子科等地， 一枪未打顺利地进占牟定城，守城的敌人早已闻风逃窜。\n\n4 月 1 7 日\n向姚安县前进。凌晨3时半出发，经过天台寺、梵 仙乡、云部乡(火烧屯)、大方定、前场关(新街子),下午2时许顺利无阻地到达姚安城。\n\n\n4 月 1 8 日\n在姚安城休息，进行扩红突击，补充部队。下午5时 许，滇敌扰乱县城。我军向西转移，经过板桥，到达白塔街 宿 营 。\n\n\n4 月 1 9 日\n向北前进，经过大桥坡、杏伍等地，顺利地进入盐 丰城。\n\n4 月 2 0 日\n向西转移，经过桥头哨、孔仙桥、土场等地，到达黄草 哨宿营，走了135里。\n\n4 月 2 1 日\n向牛井街前进，经过米甸街、猴菁等地，到达宾川 (即周城)宿营。昨天二军团之一部攻克该城，击毙守城乡兵100余名，停虏三四百人，活捉县长一名。\n\n\n4 月 2 2 日\n上午5时由宾川城出发，经过牛井街，到达鸡平关。 此地房子稀少，粮食缺乏，有部分部队露营。\n\n4 月 2 3 日\n凌晨3时出发，经过邓川县第五区黄坪、百户营， 到达鹤庆县第四区姜营宿营。下午5时开连以上政治  干部会议，张主任报告，快要与红一、四方面军会合。\n\n4 月 2 4 日\n上午5时出发，向西北方向前进，经过松桂街，到达 鹤庆县的波罗庄宿营。\n\n4 月  2 5 日\n凌晨3时出发，向西北前进，经过桃树河、长岗河，到 达鹤庆城。城内约有2000间以上房子，生意不甚发达，通 行货币尚以外圆内方孔的古铜钱为交易，这可见该地封 建之一斑矣!\n\n4 月 2 6 日\n凌晨2时出发，向北前进，经过西山、石灰窑、视榄 坝、九河、港口，到达丽江县之石鼓宿营。此地距河一 二里。走了一百三四十里。\n\n4 月 2 7 日\n上午6时出发，到达丽江县第五区第一乡(木柱地) 渡金沙江，只有一只船，因二军团尚有一部分未过完，故 等待了几点钟才渡河。十六师在我们渡河的上头十几 里的地方渡河，十七师在石鼓选择渡河地点渡河，顺利地 渡过金沙江后，在松林里集合、休息、睡觉；下午3时许， 继续向北前进，到达中甸县之四列宿营。\n\n4 月 2 8 日\n上午5时半出发，沿金沙江北L,  经过车竹、堆满村， 到达中甸县第三区梧竹开文村，只走30里。\n\n4 月 2 9 日\n在梧竹开文村休息。孙敌（孙渡）先头部队已到车竹对 河，与我十七师五十一团警戒部队接触。\n\n4 月 3 0 日\n凌晨3时出发，继续沿金沙江北进：经过雪洛、大子 坝、土所邑、木可榕，梭布湾，到达格罗湾宿营。",
      "weather": "",
      "char_count": 1553,
      "diary_id": "王恩茂日记",
      "diary_name": "《王恩茂日记》——红军长征到“七七“事变前夕",
      "diary_index": 1
    },
    {
      "date_raw": "5 月 1 日",
      "year": 1936,
      "month": 5,
      "day": 1,
      "text": "红五月一号，为着充分准备通过由格罗湾到小中甸 中间的大雪山，故在格罗湾休息一天，收集通过雪山的资 材。下午4时全军直集合，由张主任、肖军团长〔2〕报告与 中央红军会合的意义及过雪山应注意的事项。",
      "weather": "",
      "char_count": 97,
      "diary_id": "王恩茂日记",
      "diary_name": "《王恩茂日记》——红军长征到“七七“事变前夕",
      "diary_index": 1
    },
    {
      "date_raw": "5 月 2 日",
      "year": 1936,
      "month": 5,
      "day": 2,
      "text": "红五月二号，上午5时出发，向北前进，上了100里的 高山，山上尚有一尺至二尺厚的白雪，虽是红色五月然犹 如十二月一样冷的气候。下山40里才有房屋即小中甸， 即在该地宿营。该地番族（藏族）颇多，房子、风俗、习惯均与 其他民族大大不同。",
      "weather": "",
      "char_count": 116,
      "diary_id": "王恩茂日记",
      "diary_name": "《王恩茂日记》——红军长征到“七七“事变前夕",
      "diary_index": 1
    },
    {
      "date_raw": "5 月 3 日",
      "year": 1936,
      "month": 5,
      "day": 3,
      "text": "上午6时出发，军直与教导团集合，由肖军团长讲 话，总结过雪山的经验与教训，主要的在雪山上不可因疲 倦而休息，不可因口干而喝冷水，要多穿衣服裹好脚，要 带生姜、辣椒、火酒等。有个别同志在雪山上牺牲的，就因 为在雪山上休息或吃冷水等的缘故。讲话后继续向北前 进，经过菁口到大南坝一线宿营(大南坝离中甸县15 里 ) 。\n\n5月4 B\n仍在大南坝休息，筹备粮食，但因此地粮食缺乏，终 难找到粮食，只是吃一点青稞充饥。",
      "weather": "",
      "char_count": 205,
      "diary_id": "王恩茂日记",
      "diary_name": "《王恩茂日记》——红军长征到“七七“事变前夕",
      "diary_index": 1
    },
    {
      "date_raw": "5 月 5 日",
      "year": 1936,
      "month": 5,
      "day": 5,
      "text": "上个5时半向中甸城转移，7时许到达中甸县城。此 县城为我们进的城巾中最落后的一个，没有什么东西买， 虽有点糖、麦粉、盐巴，买也要到喇嘛寺去才有买。同时番 民[1 居多，与他们语言殊感困难。下午6时，军团政治部 召集军直与十七师的政治干部开会，王政委报告目前政 治与当前的工作，张主任报告关于番民工作的策略、路 线。",
      "weather": "",
      "char_count": 157,
      "diary_id": "王恩茂日记",
      "diary_name": "《王恩茂日记》——红军长征到“七七“事变前夕",
      "diary_index": 1
    },
    {
      "date_raw": "5 月 6 日",
      "year": 1936,
      "month": 5,
      "day": 6,
      "text": "在中甸城休息，同样充分准备粮食，以便顺利通过从 中甸至定乡中间的荒凉地区。",
      "weather": "",
      "char_count": 37,
      "diary_id": "王恩茂日记",
      "diary_name": "《王恩茂日记》——红军长征到“七七“事变前夕",
      "diary_index": 1
    },
    {
      "date_raw": "5 月 8 日",
      "year": 1936,
      "month": 5,
      "day": 8,
      "text": "7、8日均在中甸体息。",
      "weather": "",
      "char_count": 11,
      "diary_id": "王恩茂日记",
      "diary_name": "《王恩茂日记》——红军长征到“七七“事变前夕",
      "diary_index": 1
    },
    {
      "date_raw": "5 月 9 日",
      "year": 1936,
      "month": 5,
      "day": 9,
      "text": "午前6时出发，向北前进，下午1时半到达格咱。是日 从中甸城到格咱， 一路都是山林，没有房子。\n\n5 月 1 0 日\n午前6时出发，经过都是山地，但道路比较平坦，下 午2时许到达翁上。该地只有几栋房子，我们全部露营， 好在没有下雨，亦很安全地度过了这一夜。\n\n5 月 1 1 日\n午前5时半出发，翻了一个大坡，上下约四五十里， 继续又翻了一个小坡，上下约十余里。沿途没有人烟，山  林茂盛，有些地力尚有白雪，午后1时许到达翁水。\n\n5 月 1 2 日\n午前6时出发，走了约四五十里的平路即翻大山，翻 山时即下大雪。人上山头晕、眼花、气喘，下山五六十里， 沿途均卜大雪，满地雪白，再走几里没有雪了，才到易窝 宿营。此时已午后6时半了，共走了100里以上。\n\n5 月 1 3 日\n午前7时出发，本来要抵定乡城宿营，因路经易井， 人烟比较稠密，粮食不成问题，同时顾及部队的疲劳，即 在易井宿营，走了五十余里。是日，十七师胜利地占领了 定乡城，城内番民群众送麦粉、青稞粉，欢迎红军。\n\n5 月 1 4 日\n午前6时许出发，午后1时到达定乡城。\n\n\n5 月 1 5 日\n在定乡城休息。政治部开部务会议，讨论休息三天工 作及检查从中甸出发到定乡时期中的工作。\n\n5 月 1 6 日\n在定乡城休息。\n\n\n5 月 1 7 日\n在定乡城休息。召集全军团积极分子会议，王政委作 报告，说明目前政治形势与会师西北，创造全国抗日根据 地的优越条件及其伟大政治意义与战斗任务。\n\n\n5 月 1 8 日\n继续在定乡城休息。\n\n\n5 月 1 9 日\n还是在定乡城休息。准备20日向稻城城前进。\n\n\n5 月 2 0 日\n向稻城城前进。上午5时半出发，沿硕楚河而上，经 过义司出、沙村、归日、喜友，到水洼休息半小时，再前进 至百根宿营。经过地区都有房屋、田垅，路旁有不少的番 民群众卖东西，并烧茶送给我们吃。这是由于我们在定乡 城传播了党和苏维埃对少数民族政策的影响的结果。\n\n5 月 2 1 日\n上午5时半出发，继续沿硕楚河而上，经过沙古、相 店，即上坡30余里。山上尚有部分白雪没有融完。下山30 余里，到达桑川宿营。沿途多系大山，没有房子，气候比定 乡要冷，后面掉队的在山上还遇到了大雪。\n\n5 月 2 2 日\n上午6时出发，满地白霜，气候犹如冬天，经过地带 都是平地，但很荒凉，极少人烟，下午1时许到达稻城城。 该县没有城墙和街道，只有十几栋零散的房子，和乡下没  有什么分别，但不过有五个喇嘛寺。群众粮食很少，多是  吃牛、羊，山上柴火也少，多是烧牛粪。\n\n5 月 2 5 日\n23、24、25日，均在稻城休息。25日开晚会，首先由肖 军团长报告分散教导团的意义，主要的不是什么处在严 重环境要减少单位，便利指挥行动，而是为了加强部队的 教育训练整理，需要分散干部去各部队领导。其次由吴局长（吴德峰） 报告处决组织拖枪逃跑的反革命的罪恶。\n\n5 月 2 6 日\n继续在稻城休息。下午参加全军团团以上军政干部 会议，会议主要内容是开展反倾向斗争，反对军阀残余， 反对贪污行为，反对小资产阶级意识和工作消沉的错误， 同时指出会师西北前的军事政治中心工作。\n\n5 月 2 7 日\n还在稻城休息。\n\n\n5 月 2 9 日\n28、29日因下雪，故继续在稻城休息。",
      "weather": "",
      "char_count": 1363,
      "diary_id": "王恩茂日记",
      "diary_name": "《王恩茂日记》——红军长征到“七七“事变前夕",
      "diary_index": 1
    },
    {
      "date_raw": "5 月 30  日 天晴。",
      "year": 1936,
      "month": 5,
      "day": 30,
      "text": "向藏坝前进，经过冉子，到达大桥宿营。\n\n\n5 月 3 1 日 天晴。\n凌晨4时半出发，经过 一 个30里和 一 个60里的山， 但路程很近，所以12时即到达了拉波。",
      "weather": "",
      "char_count": 82,
      "diary_id": "王恩茂日记",
      "diary_name": "《王恩茂日记》——红军长征到“七七“事变前夕",
      "diary_index": 1
    },
    {
      "date_raw": "6 月 1 日",
      "year": 1936,
      "month": 6,
      "day": 1,
      "text": "因昨夜下大雨，从拉波至德巫有一个大山，为了避免 下雨过山掉队落伍增加的现象，故在拉波休息一天，准备 过山的一切事宜。",
      "weather": "",
      "char_count": 58,
      "diary_id": "王恩茂日记",
      "diary_name": "《王恩茂日记》——红军长征到“七七“事变前夕",
      "diary_index": 1
    },
    {
      "date_raw": "6 月 2 日",
      "year": 1936,
      "month": 6,
      "day": 2,
      "text": "上午6时出发，走了80里，下毛毛雨，经过地区都是 崎岖上下，翻了一个坡又一个技，但是每个坡都不高大。 沿途没有房子。本来到德巫宿营，因前卫走错了路：超过 了德巫，向藏坝前进，再走50里，到藏坝宿营。但这50里 很蛮，要当80里，同时最后还有一个高雪山，所以摸了二  三十里夜路；掉队落伍的很多，到达藏坝房子很少，有部 分队伍露营。",
      "weather": "",
      "char_count": 165,
      "diary_id": "王恩茂日记",
      "diary_name": "《王恩茂日记》——红军长征到“七七“事变前夕",
      "diary_index": 1
    },
    {
      "date_raw": "6 月 3 日",
      "year": 1936,
      "month": 6,
      "day": 3,
      "text": "下雨和雪。\n上午9时听见九军团(三十二军)来了代表在军 团部，他们在呷洼木拉一线等我们一个多星期了，我们非 常兴奋。10时向九军团附近转移，将到呷洼附近，九军团 排列队伍欢迎我们，并有化装跳舞等慰劳我们。沿途用木 板竖起，上面贴着艺术字的标语：“欢迎善打运动战、河川 战的二、六军”、“学习二、六军巩固部队的经验”、“会合 二、六军消灭卖国匪军” ……到呷注寺门前，又有九军团 部队炊迎，并有很多番民群众参加欢迎。我们即宿营于呷 注寺，与九军团司令部一起驻着。",
      "weather": "",
      "char_count": 230,
      "diary_id": "王恩茂日记",
      "diary_name": "《王恩茂日记》——红军长征到“七七“事变前夕",
      "diary_index": 1
    },
    {
      "date_raw": "6 月 4 日",
      "year": 1936,
      "month": 6,
      "day": 4,
      "text": "天晴。\n参加中共西康南路工作委员会的会议，了解了九军 团的一些情形，与一、四方面军会合的经过及其分裂的原 因，以及目前反右倾机会土义、反逃跑退却的重大意义。",
      "weather": "",
      "char_count": 78,
      "diary_id": "王恩茂日记",
      "diary_name": "《王恩茂日记》——红军长征到“七七“事变前夕",
      "diary_index": 1
    },
    {
      "date_raw": "6 月 5 日",
      "year": 1936,
      "month": 6,
      "day": 5,
      "text": "半晴半阴。\n举行十六师与三十二军的联欢人会，有王、肖、罗（罗炳辉）等演说。",
      "weather": "",
      "char_count": 37,
      "diary_id": "王恩茂日记",
      "diary_name": "《王恩茂日记》——红军长征到“七七“事变前夕",
      "diary_index": 1
    },
    {
      "date_raw": "6 月 6 日",
      "year": 1936,
      "month": 6,
      "day": 6,
      "text": "上午十七师来了，举行全军团与三十二军的联欢会， 有罗、刘（刘转连）的报告及九军团的新剧。下午参加全军团排 以上的干部会议。",
      "weather": "晴",
      "char_count": 61,
      "diary_id": "王恩茂日记",
      "diary_name": "《王恩茂日记》——红军长征到“七七“事变前夕",
      "diary_index": 1
    },
    {
      "date_raw": "6 月 7 日",
      "year": 1936,
      "month": 6,
      "day": 7,
      "text": "仍在呷注寺休息。五十一团与三十二军出发。",
      "weather": "",
      "char_count": 20,
      "diary_id": "王恩茂日记",
      "diary_name": "《王恩茂日记》——红军长征到“七七“事变前夕",
      "diary_index": 1
    },
    {
      "date_raw": "6 月 8 日",
      "year": 1936,
      "month": 6,
      "day": 8,
      "text": "下 雨 。\n仍在呷洼寺休息。前方来电，五十…团于7日午后3 时攻克理化,击溃守城之卖国军李抱冰部,反动喇 嘛均纷纷投诚。",
      "weather": "",
      "char_count": 60,
      "diary_id": "王恩茂日记",
      "diary_name": "《王恩茂日记》——红军长征到“七七“事变前夕",
      "diary_index": 1
    },
    {
      "date_raw": "6 月 9 日",
      "year": 1936,
      "month": 6,
      "day": 9,
      "text": "午前6时许出发，向理化前进。经过路途都很平坦， 特别是离理化30里路的中间都是大坝子，可惜没有一点 种植业。下午4时才到达理化。\n\n6 月 1 0 日\n晴。\n在理化休息。得接通报，从本日起在理化休息三天。\n\n\n6 月 1 1 日\n晴 .\n在理化休息。闻中央电报，两广爆发反蒋武装行 动,并出兵占领湖南衡阳,白崇禧为反蒋革命军前 敌总指挥，李宗仁、陈济棠为副司令。\n\n6 月 1 2 日\n原命令向瞻化前进，后改了命令，仍在理化休息 一 天 。\n\n6 月 1 3 日\n晴。\n上午6时半出发，经过地区都是荒山草地，时晴时 雪。本来要到牙坝宿营，因路程太远(130里),天黑了，走 了十几里夜路，到离牙坝30里的树林里露营。天气很冷， 有些战士全靠烤火过夜，好在没有下雨，我们很安全地过 了 一 夜 。\n\n6 月 1 4 日\n本来要到阿宿，因昨天走路太多，士兵疲劳，掉队的 颇多，故走30里即在牙坝宿营。\n\n6 月 1 5 日\n经过60里，翻了一个山，到达阿宿宿营。是日，经过 地方比较暖和，沿途都有房子，并有青蓬蓬的麦子。\n\n\n6 月 1 6 日\n经过80里，共翻了三个坡，最后下一个大坡约有二 三十里，到达麻日宿营。四方面军来了代表迎接我们。\n\n6 月 1 7 日\n晴。\n本来到博孜宿营，因要迅速与四方面军会合，故赶到 瞻化，走了110里，离瞻化二0里路的地方，即有四方面军 政治部欢迎我们的标语。到达瞻化时，有四方面军直属部 队整队欢迎。\n\n\n6 月 1 8 日\n\n上午晴，下午雨。\n在瞻化休息。下午2时与四方面军开联欢大会。\n\n\n6 月 1 9 日\n晴。\n从瞻化出发，沿雅砻江而上，经过60里，路较平坦， 下午2时到热洛宿营。\n\n6 月 2 0 日\n晴。\n上午5时出发，继续沿雅砻江而上，到波洱过桥渡雅 砻江，经过90里，下午3时许到达大盖宿营。\n\n6 月 2 1 日\n晴。\n上午6时出发，还是沿雅砻江而上，经过60里，到达 沙灯宿营。\n\n6 月 2 2 日\n晴。\n上个6时出发，经过五六十甲，与红三十军会合， 到达普玉隆宿营。将到普玉隆的地方，有总政治部、中央  剧社、三十军、番民独立军等欢迎。\n\n6 月 2 3 日\n晴。\n上午在普玉隆休息，下午移房子。\n\n\n6 月 2 4 日\n晴。\n上午到二十军吃饭，下午4时参加会师大会。首先由 王政委介绍中央各革命领袖，次由张主任主持会议。开头  朱总司令（朱德）报告，继续有西北局组织部长傅钟同志、 总政委张国焘同志、总政主任陈昌浩同志、中央政府代表  何长工同志等报告，后由肖军团长答词。中央剧社演 剧，至天黑热烈散会。\n\n6 月 2 5 日\n晴 。\n到甘孜城，去总政治部和西北局找文件看。\n\n\n6 月 2 6 日\n晴。\n总政治部组织参观团参观六军团，我率一组去参观 模范师(原四十九团)。同时，是日召集全军连以上干部会 议，有朱总司令、刘总参谋长（刘伯承）报告。我因参加参观去 了，未参加是会。\n\n\n6 月 2 7 日\n晴 。\n本来六军团组织参观团去参观四方面军，因三十军 说来参观，故未去，但是三十军也未来参观。上午7时，召 集全军连以上干部会议，报告西北问题，报告者    陈昌 浩同志，我参加听了。\n\n6 月 2 8 日\n晴：\n(一)六军团代表去参观四方面军；(二)我起草运动 战中政工报告；(三)下午，全军团开全军连以上参加的军 事会议，报告西北地区行军、宿营、作战的事项。\n\n\n6 月 2 9 日\n晴 。\n写完运动战中政治工作报告，\n\n\n6 月 3 0 日\n晴。\n六军团移房子到甘海子。我本即日去甘海子，因要随 王、张到甘孜，故未即日去，而于上午11时到达甘孜， 宿于总政。",
      "weather": "晴",
      "char_count": 1517,
      "diary_id": "王恩茂日记",
      "diary_name": "《王恩茂日记》——红军长征到“七七“事变前夕",
      "diary_index": 1
    },
    {
      "date_raw": "7 月 1 日",
      "year": 1936,
      "month": 7,
      "day": 1,
      "text": "在甘孜总政休息。下午四五时，二军团军团长贺龙、政委任弼时率一排人到了甘孜与四方面军会合〔1",
      "weather": "晴",
      "char_count": 45,
      "diary_id": "王恩茂日记",
      "diary_name": "《王恩茂日记》——红军长征到“七七“事变前夕",
      "diary_index": 1
    },
    {
      "date_raw": "7 月 2 日",
      "year": 1936,
      "month": 7,
      "day": 2,
      "text": "上午晴，下午雨。\n二军团四师和军直下午3时到甘孜。",
      "weather": "",
      "char_count": 25,
      "diary_id": "王恩茂日记",
      "diary_name": "《王恩茂日记》——红军长征到“七七“事变前夕",
      "diary_index": 1
    },
    {
      "date_raw": "7 月 3 日",
      "year": 1936,
      "month": 7,
      "day": 3,
      "text": "上午5时由甘孜城出发，沿途休息很久，下午3时许 到达甘海子。",
      "weather": "晴",
      "char_count": 30,
      "diary_id": "王恩茂日记",
      "diary_name": "《王恩茂日记》——红军长征到“七七“事变前夕",
      "diary_index": 1
    },
    {
      "date_raw": "7 月 4 日",
      "year": 1936,
      "month": 7,
      "day": 4,
      "text": "在甘海子休息，准备北上工作。",
      "weather": "晴",
      "char_count": 14,
      "diary_id": "王恩茂日记",
      "diary_name": "《王恩茂日记》——红军长征到“七七“事变前夕",
      "diary_index": 1
    },
    {
      "date_raw": "7 月 5 日",
      "year": 1936,
      "month": 7,
      "day": 5,
      "text": "还在甘海子休息。",
      "weather": "晴",
      "char_count": 8,
      "diary_id": "王恩茂日记",
      "diary_name": "《王恩茂日记》——红军长征到“七七“事变前夕",
      "diary_index": 1
    },
    {
      "date_raw": "7 月 6 日",
      "year": 1936,
      "month": 7,
      "day": 6,
      "text": "上午在甘海子休息，下午1时出发，5时到达东谷宿 营。东谷房子很多并很漂亮，为我到西康未见之乡村。",
      "weather": "晴",
      "char_count": 48,
      "diary_id": "王恩茂日记",
      "diary_name": "《王恩茂日记》——红军长征到“七七“事变前夕",
      "diary_index": 1
    },
    {
      "date_raw": "7 月 7 日",
      "year": 1936,
      "month": 7,
      "day": 7,
      "text": "上午5时半出发，经过约百里，均无房屋，到达大吉 岭前进约十里露营。这次露营很好，有山林可取柴烧，有 小河可取水喝。因此虽然露营，要比房子不大好的地方宿 营好得多，可惜天捣鬼，半夜下起雨来了，弄得我们无可 奈何，睡也睡不好，被毯也打湿了。",
      "weather": "晴",
      "char_count": 118,
      "diary_id": "王恩茂日记",
      "diary_name": "《王恩茂日记》——红军长征到“七七“事变前夕",
      "diary_index": 1
    },
    {
      "date_raw": "7 月 8 日",
      "year": 1936,
      "month": 7,
      "day": 8,
      "text": "下 雨 。\n凌晨4时出发，本来到离日庆40里的地方露营，但我 们走得快，走到了日庆的地方露营。同样夜晚落雨，弄得 我们不安。",
      "weather": "",
      "char_count": 62,
      "diary_id": "王恩茂日记",
      "diary_name": "《王恩茂日记》——红军长征到“七七“事变前夕",
      "diary_index": 1
    },
    {
      "date_raw": "7 月 9 日",
      "year": 1936,
      "month": 7,
      "day": 9,
      "text": "在日庆休息。夜晚露营，没有下雨。\n\n\n7 月 1 0 日\n凌晨晴，下午雨。\n上个3时半出发，经过75里，12时到达唐牙沟露营。 夜晚下一夜雨，把我们的毯子、衣服都打湿了，真不好过。\n\n7 月 1 1 日\n上午晴，下午雨。\n上午5时半出发，下午7时半到达西倾寺宿营。夜晚 下一夜雨，好在有房子宿营。如没有房子，又是一夜不好 过 。从唐牙沟到西倾寺，其名60里，实则100里还有余。\n\n7 月 1 2 日\n早晨雨。\n在西倾寺休息，准备七天粮食，但因番民喇嘛逃跑， 粮食都搬走与埋藏了，不但没有收集七天粮食，而且在西 倾寺休息吃的粮食都没有。部队粮食整个说起来只能吃 二三天，有的没有了。为着节省带的粮食于继续过草地时 吃起见，故部队一律采取野菜充饥。\n\n\n7 月 1 3 日\n早晨雨，中午四面浮云遮天，欲雨未雨，下午又雨。\n5时半出发，经过鱼头寺进沟，沿沟而上，翻了两个 山，下午8时才到绒玉宿营。最后一个山比较高，下山很 陡，同时又滑，天又黑了，真不好下。是日， 一天完成两天 行程，路约走了120里。\n\n7 月 1 4 日\n雨 。\n在绒玉休息，没有粮食吃，吃野菜。\n\n\n7 月 1 5 日\n阴 。\n还在绒玉休息，同样吃野菜过日子。\n\n7 月 1 6 日\n晴。\n上午7时半由绒玉出发，沿河而上，在路上休息数 次，看见很多猴子在山上，下午3时到达王楼宿营。各部 队同样没有找到粮食，仍然吃野菜。\n\n7 月 1 7 日\n雨 。\n上午5时出发即上坡，路途湿滑，不好走，加之没有 粮食，吃野菜充饥，两脚没有力，更是难走。下午1时到达 哑龙寺宿营。\n\n7 月 1 8 日\n晴。\n在哑龙寺一线休息，补充粮食。但因该地没有群众， 前卫部队收集粮食去了，所以未补充什么粮食，各部队多 是采野菜做干粮。只有十八师在打牛场，打了60多头牛， 还找到1000多斤麦子。\n\n7 月 1 9 日\n凌晨晴，下午大雨。\n上午4时半出发，经过都是山冲平路，12时半到达作 木沟露营。其名是日走了80里，实则只有五六十里。到达 该地不久，即大风大雨，并下大雪雹，坠头很痛。这夜露 营，打得满身通湿，早晨起来特别寒冷，大有如我家乡三 冬气候。\n\n\n7 月 2 0 日\n雨 。\n上午6时出发，本来到过木寺宿营，只有60里，但是 走了一天整，到下午5时，尚没有找到过木寺。后来才知 道没有过木寺这个地方，就在离作木沟八九十里的沟里 露营。此时满天黑云，大有下大雨的形势，并已下微雨。大 家都忧虑着今天睡不安全，要被雨捣乱，然而停一会儿， 雨停了，一夜没有下雨，很好地睡了一夜，只是很冷。\n\n7 月 2 1 日\n上午阴，出了一下太阳，下午雨。\n上午5时出发，大家希望今天到阿坝(因为没有 粮食，大家希望到阿坝补充粮食，吃几餐饱糌粑),但是走 了一天，到下午3时，碰到中革军委总政治部送牛几百头，给我们做粮食的，说到阿坝还有40多里，于是我们就 在离阿坝40多里的地方露营。这天夜晚下一夜雨，帐篷 大漏，地下很湿，睡觉不安，总是等待着快点天亮好出发。\n\n7 月 2 2 日\n雨 。\n上午5时出发，土一个坡，过一个约40里路的横排 山。正在过横排山时，下大雨，刮大风，天气非常冷，手冻 不能伸。过完横排山，即看见阿坝，很大的田地，很多的房 子，加之太阳从云钻出来，天气转暖，个个精神大大的兴 奋，一直下山，勇往直前地到达下阿坝。我到教导团动员 筹粮队去收集粮食。\n\n7 月 2 3 日\n上午晴，下午雨。\n在下阿坝动员收集粮食，收集了6万多担，供应本军 给养。准备继续通过10天草地，到达松潘。过去在廿 海子时准备粮食不充分，以致从西倾寺起一直到阿坝止， 11天期间，全军没有粮食，全靠吃野菜、牛皮充饥，影响部  队，掉队落任、死亡和逃跑现象严重。这一血的教训，要求  我们在阿坝加紧收集粮食。\n\n7 月 2 4 日\n上午雨，下个阴、晴。\n我到模范师帮助收集粮食突击的动员。\n\n\n7 月 2 5 日\n阴 。\n在政治部。\n\n\n7 月 2 6 日\n晴。\n上午11时准备完毕，开至大金川边等待渡河。下午2 时渡河完结，即在河之东岸休息约两小时，始向中阿坝开 动，7时半到达中阿坝。\n\n7 月 2 8 日\n晴 。\n27、28日均在中阿坝休息。\n\n\n7 月 2 9 日\n晴。\n上午6时由中阿坝移驻下阿坝，走了约20里。\n\n7 月 3 0 日\n上午晴，下午雨。\n上午5时由下阿坝出发，经过都是青山、草地，没有 森林、房屋。将露宿时，突然一阵强风暴雨并加雪雹，打得 我们缩住头颈不敢一动。后风雨稍停，仍前进到离下阿坝 65里的地方贾诺露宿。夜晚下一夜雨。\n\n7 月 3 1 日\n雨 ，\n上午5时出发，经过都是水草地，有些地方人马堕脚 不能出。是日，本来要到箭步塘露宿，但因十六师走错了 路，离箭步塘尚有一天路程的地方宿。夜晚同样下雨。",
      "weather": "晴",
      "char_count": 1985,
      "diary_id": "王恩茂日记",
      "diary_name": "《王恩茂日记》——红军长征到“七七“事变前夕",
      "diary_index": 1
    },
    {
      "date_raw": "8 月 1 日",
      "year": 1936,
      "month": 8,
      "day": 1,
      "text": "上午5时出发，经过地方同样是水草地。下午3时到 达箭步塘前面几里路的地方露营。",
      "weather": "雨",
      "char_count": 39,
      "diary_id": "王恩茂日记",
      "diary_name": "《王恩茂日记》——红军长征到“七七“事变前夕",
      "diary_index": 1
    },
    {
      "date_raw": "8 月 2 日",
      "year": 1936,
      "month": 8,
      "day": 2,
      "text": "上个雨，下午晴。\n上午5时出发，经过地方还是水草地。因要赶到郭曲 河(黄河支流)露营，所以走到日头下山，月亮出山一丈多 高，约8点钟时，才到郭曲河宿营。据说从箭步塘到郭曲 河只有90里，实际上100里犹不止。",
      "weather": "",
      "char_count": 104,
      "diary_id": "王恩茂日记",
      "diary_name": "《王恩茂日记》——红军长征到“七七“事变前夕",
      "diary_index": 1
    },
    {
      "date_raw": "8 月 3 日",
      "year": 1936,
      "month": 8,
      "day": 3,
      "text": "上午7时顺利渡过郭曲河，到达河东坪露营，休息一 · 天。",
      "weather": "晴",
      "char_count": 28,
      "diary_id": "王恩茂日记",
      "diary_name": "《王恩茂日记》——红军长征到“七七“事变前夕",
      "diary_index": 1
    },
    {
      "date_raw": "8 月 4 日",
      "year": 1936,
      "month": 8,
      "day": 4,
      "text": "上午6时出发，经过的草地比以前经过的要好些，沿 途有点森林，下午3时半到牙磨河露营。",
      "weather": "晴",
      "char_count": 42,
      "diary_id": "王恩茂日记",
      "diary_name": "《王恩茂日记》——红军长征到“七七“事变前夕",
      "diary_index": 1
    },
    {
      "date_raw": "8 月 5 日",
      "year": 1936,
      "month": 8,
      "day": 5,
      "text": "早晨下丽，约2点钟就天晴。\n上午5时出发，经过地方有一半水草地， 一半干草 地。下午1时半到达离上、中色既塘60余里的地方露营。",
      "weather": "",
      "char_count": 64,
      "diary_id": "王恩茂日记",
      "diary_name": "《王恩茂日记》——红军长征到“七七“事变前夕",
      "diary_index": 1
    },
    {
      "date_raw": "8 月 6 日",
      "year": 1936,
      "month": 8,
      "day": 6,
      "text": "上午5时出发，经过大多数地方是水草地。下午2时 到达色既塘露营。",
      "weather": "晴",
      "char_count": 32,
      "diary_id": "王恩茂日记",
      "diary_name": "《王恩茂日记》——红军长征到“七七“事变前夕",
      "diary_index": 1
    },
    {
      "date_raw": "8 月 7 日",
      "year": 1936,
      "month": 8,
      "day": 7,
      "text": "上午4时半出发，经过的地方还有  部分水草地，人 马不好走，有些马匹跌在泥坑里不能起来。过了一个比较 大的山，山上气候很冷。下午5时半，超过了岩朵坝20里 露 营 。",
      "weather": "晴",
      "char_count": 83,
      "diary_id": "王恩茂日记",
      "diary_name": "《王恩茂日记》——红军长征到“七七“事变前夕",
      "diary_index": 1
    },
    {
      "date_raw": "8 月 8 日",
      "year": 1936,
      "month": 8,
      "day": 8,
      "text": "凌晨4时出发，顺利地通过了草地，下午5时到达上 包座宿营。从阿坝出发以来，整个九天没有住房子，是日 开始住房子，完成了北上第一个战役阶段。",
      "weather": "晴",
      "char_count": 69,
      "diary_id": "王恩茂日记",
      "diary_name": "《王恩茂日记》——红军长征到“七七“事变前夕",
      "diary_index": 1
    },
    {
      "date_raw": "8 月 9 日",
      "year": 1936,
      "month": 8,
      "day": 9,
      "text": "上午6时从上包座出发，经过中包座，下乍4时到达 下包座宿营。\n\n8 月 1 0 日\n晴。\n上午6时移房子到下包座喇嘛寺，\n\n8 月 1 5 日\n雨 。\n从11日起到今天，均在下包座休息。\n\n\n8 月 1 6 日\n阴。\n凌晨4时从下包座出发，经过救济寺，下午1时到达 离救济寺下18里的地方宿营。是日，从草地行军转入于 山地行军。\n\n\n8 月 1 7 日\n阴。\n下午5时出发，经过蔡里公坝，再前进约10余里的地方宿营。这天经过多系隘路，两边岩山壁立，并通过数处 桥梁，均甚险要。\n\n8 月 1 8 日\n雨 。\n上午5时出发，到达俄碛公坝(即俄界)。因前八里的 地方有一个卡子，反动武装在那里打枪，五军经过时 伤亡数十名。我们为避免无谓之损失，决定夜行军通过， 故白日在俄界休息，进行夜行军准备。但因白龙江河水骤  涨，淹没道路，不能通过，所以是日夜晚没有夜行军。\n\n8 月 1 9 日\n\n阴。\n因为18日夜未实行夜行军，白天不能通过俄界前面 八里的卡子，故在俄界休息、下午6时出发，夜行军通过 前面八里的卡子，到达离俄界约20里的地方露营，\n\n8 月 2 0 日\n晴 。\n凌晨4时半出发，走了10余里大休息，下午2时继续 前进，超过下卡四五里露营。\n\n8 月 2 1 日\n晴。\n凌晨4时半出发，继续沿白龙江而下，经过哇藏寺、 石门、万险桥、莫乐，到达麻牙寺宿营。\n\n8 月 2 2 日\n晴。\n上午5时半出发，下午4时半到达视庄宿营。视庄离 洛大尚有10余里，此地有回民群众卖东西。这是我们经 过月余草地行军未见群众，今日是开始看见群众的一天。\n\n8 月 2 3 日\n晴。\n上午5时出发，本来到大拉山宿营，但因天快黑了， 同时大拉山房子不多，即在离大拉山10里的地方    绪  里其(曹子里)宿营。\n\n8 月 2 4 日\n晴。\n上午5时出发，向哈达铺前进，到大拉山，翻了一个 上下各约15里路的山，再走20余里形似草地的地区，到 先窝泥，一路有房子、粮食、群众。经过约10里，到达麻子 场宿营。\n\n8 月 2 5 日\n阴。\n凌晨4时出发，到达哈达铺。\n\n\n8 月 2 6 日\n阴。\n在哈达铺休息，与九军直属队开联欢大会。\n\n8 月 2 7 日\n雨。\n仍在哈达铺休息。\n\n8 月 2 8 日\n雨 。\n本来出发，但因下雨仍在哈达铺休息。\n\n\n8 月 2 9 日\n晴。\n上午7时出发，经过理川、板里庄等地，下午6时半到 达岷县之闾井镇宿营。\n\n8 月 3 0 日\n晴 。\n在间井镇休息。\n\n\n8 月 3 1 日\n晴。\n我军决定以夺取礼县为目的，继续向礼县前进。 凌晨4时半出发，经过沙金沟、座家里等地，下午5时半到 达岷县之马坞镇宿营。",
      "weather": "晴",
      "char_count": 1114,
      "diary_id": "王恩茂日记",
      "diary_name": "《王恩茂日记》——红军长征到“七七“事变前夕",
      "diary_index": 1
    },
    {
      "date_raw": "9 月 1 日",
      "year": 1936,
      "month": 9,
      "day": 1,
      "text": "继续向礼县前进，下午6时到达榻板里(离礼城3 里)。因礼县未攻克，即在榻板里宿营。",
      "weather": "晴",
      "char_count": 41,
      "diary_id": "王恩茂日记",
      "diary_name": "《王恩茂日记》——红军长征到“七七“事变前夕",
      "diary_index": 1
    },
    {
      "date_raw": "9 月 2 日",
      "year": 1936,
      "month": 9,
      "day": 2,
      "text": "在榻板里休息，下乍4时移驻礼城之西北门外小村 子。",
      "weather": "晴",
      "char_count": 25,
      "diary_id": "王恩茂日记",
      "diary_name": "《王恩茂日记》——红军长征到“七七“事变前夕",
      "diary_index": 1
    },
    {
      "date_raw": "9 月 3 日",
      "year": 1936,
      "month": 9,
      "day": 3,
      "text": "在礼县之西北门外小村子里休息。敌机来了几次，掩 护由西和县增援礼县之敌人，约一团之众进礼城。我 们为便利休息、整理以及在运动战中消灭敌人，故于下午 6时半转移新地区，夜行军四五小时，到达额园里(离宗传 里五里)宿营",
      "weather": "晴",
      "char_count": 107,
      "diary_id": "王恩茂日记",
      "diary_name": "《王恩茂日记》——红军长征到“七七“事变前夕",
      "diary_index": 1
    },
    {
      "date_raw": "9 月 5 日",
      "year": 1936,
      "month": 9,
      "day": 5,
      "text": "4.5日均在额园里休息。",
      "weather": "阴",
      "char_count": 12,
      "diary_id": "王恩茂日记",
      "diary_name": "《王恩茂日记》——红军长征到“七七“事变前夕",
      "diary_index": 1
    },
    {
      "date_raw": "9 月 8 日",
      "year": 1936,
      "month": 9,
      "day": 8,
      "text": "从6日起至今日均在崖湾里休息。",
      "weather": "晴",
      "char_count": 15,
      "diary_id": "王恩茂日记",
      "diary_name": "《王恩茂日记》——红军长征到“七七“事变前夕",
      "diary_index": 1
    },
    {
      "date_raw": "9 月 9 日",
      "year": 1936,
      "month": 9,
      "day": 9,
      "text": "上午6时由崖湾里转移于岩村。\n\n\n9 月 1 0 日\n阴 。\n在岩村休息。\n\n9 月 1 1 日\n上午雨，下午阴。\n凌晨1时出发，经过马家河、枣下河，翻了三个小小 的山，下午5时半到达永坪镇。\n\n\n9 月 1 2 日\n晴 。\n上午在永坪镇休息，12时出发，向天水镇  前进，下 个7时半到达横河镇宿营。\n\n9 月 1 3 日\n上午阴，下午雨。\n在横河镇休息。\n\n\n9 月 1 4 日\n上午雨，下午阴。\n上午在横河镇休息，下午1时出发，经过草坝，6时到 达余家坪(小地名赵家崖湾里)宿营。\n\n9 月 1 5 日\n晴。\n上车5时半出发，本米军直与模范师、十八师为左纵 队，经寻家底到达天水镇宿营，十七师与十六师经罗家铺取道至天水镇，但因天水镇有敌，故至平南川宿营。\n\n\n9 月 1 6 日\n晴。\n本军担任夺取两当县城的任务。凌晨4时出发， 向两当县城前进，经过张家峪、娘娘坝，到骆驼上大休息。 到李子园，前卫部队消灭卖国匪军一个连，缴获步枪10 余支。下午7时到达百纳峡宿营。\n\n9 月 1 7 日\n晴。\n上午6时出发，经过高桥、白杨林等地，下午6时平， 到达徽县之马家庄宿营。\n\n9 月 1 8 日\n晴。\n凌晨3时半出发，经过韩家湾，继续翻过两个山，下 午1时到达两当县城。我先头部队拂晓攻城，守城之敌全 末为之防，被我军全部消灭，缴获步枪数十支、连枪一支、收音机一架，俘获县政府全部工作人员。是口早出发时， 王政委报告：二军之  部占领成县,击溃毛炳 文一个团，缴获步枪300余支。\n\n9 月 1 9 日\n晴。\n为完成拿下凤县之任务，未在两当城休息，仍继 续向风县前进。上午5时出发，经过杨家店子、双石铺，下 午4时到达离凤城四五里的地方，模范师在攻城，但木攻 克，即在桑园宿营。\n\n\n9 月 2 0 日\n晴 。\n上午在桑园休息，下午撤凤县之围，6时出发，退回双 石铺宿营。\n\n\n9 月 2 1 日\n晴。\n上午在双石铺休息，下个敌机向双石铺旋绕数次。下 午1时出发，回两当、徽县工作，但因走到杨家店天即快 黑了，故即在杨家店宿营。\n\n9 月 2 2 日\n晴 。\n上午6时出发，经过灵官殿，下午9时到达两当城。\n\n9 月 2 9 日\n从23日起到29日均在两当城。\n\n\n9 月 3 0 日\n雨。\n由两当到杨家店检查突击扩红工作。\n\n\n1 0 月 3 日\n1日至3日均在杨家店参加突击扩红工作。\n\n\n1 0 月 4 日\n晴。\n凌晨1时由杨家店出发，天未亮即抵两当城，休息一二小时，继续前进，到达马家庄宿营。\n\n\n1 0 月 5 日\n晴。\n上午5时出发，经过白杨林、高桥等地，到达百纳峡 乂前进25里，下午9时才到李子园宿营。\n\n1 0 月 6 日\n晴。\n为了通过天水、徽县、成县敌人的封锁线，迅速与一 方面军会合，故夜行军。凌晨1时出发，经过大门镇，下午 4时到达杨家湾宿营。\n\n1 0 月 7 日\n上午阴，下午雨。\n凌晨3时出发，向横河镇前进，沿途敌人打枪，特别 是经过罗家堡时，因敌机轰炸，配合陆军动作，同时十六 师压制松懈，致使敌人出击。军直、模范师均从敌人枪林 弹雨中冲出来，下午4时半到达横河镇宿营。\n\n1 0 月 8 日\n阴。\n凌晨4时出发，下午1时到达固城附近宿营。\n\n\n1 0 月 9 日\n晴。\n为了北渡渭水，通过陕甘大道与一、四方面军会合， 凌晨3时出发，沿途休息多次，下午八九时到达五十里 铺，即渡河到达甘谷县之永安乡宿营。\n\n1 0 月 1 0 日\n雨。\n在永安休息。\n\n\n1 0 月 1 1 日\n晴。\n上午5时出发，向礼辛镇前进，沿途遭遇敌机，敌机 往返五六次，投弹五六十颗，这是我们进入甘肃遇到敌机 轰炸最厉害的一回。因为隐蔽敌机的原故，下午4时许才到礼辛镇宿营。\n\n\n1 0 月 1 2 日\n晴。\n为了避免敌机轰炸，决定夜行军，凌晨1时出发，本 来到李家店子，因走错了路到常河镇即日出几尺了，故即 在常河镇宿营。\n\n1 0 月 1 3 日\n晴。\n凌晨零时30分出发，天亮到达马家店子休息大半 天。下午3时继续出发，夜行军到通渭县之吴家村宿 营。吴家村离通渭10里。\n\n\n1 0 月 1 4 日\n晴。\n在吴家村休息大半天，下午3时出发，夜行军，经过 50里，12时到达蔡家镇宿营。\n\n1 0 月 1 6 日\n晴。\n15、16日均在蔡家镇休息。\n\n\n1 0 月 1 7 日\n晴。\n凌晨3时出发，经过40里，8时到达四沟河(寺咀 镇)。为了迅速与一方面军会合，下午3时继续行军，经过 60里到青家驿。本来即在该地宿营，但因驻了九军部队， 我们停留了好久，正是半夜，冷得厉害，又没房子宿营，要 再走20里才有房了，故即挤在九军驻的房子内宿营。\n\n1 0 月 1 8 日\n晴。\n天亮木吃早饭即出发，上午9时许到达老君铺。 一方 面军二师派了五团一部分同志来欢迎我们。\n\n10月 1 9 日\n晴.。\n在老君铺，早晨集合，十六师、十八师、模范师全部及 十七师连以上干部，欢迎红五团参观代表，请红五团  政委报告陕北苏区情况和反帝统一战线的伟大胜利。\n\n1 0 月 2 1 日\n晴。\n20、21日均在老君铺休息。\n\n1 0 月 2 2 日\n晴。\n原命令向南贻河前进，后改向公阳镇前进，经过70 里到达该地宿营。该地都是回民居住。\n\n1 0 月 2 3 日\n晴。\n凌晨4时出发，天亮即到兴隆镇,与一方面军一 军团一师会合， 一师直属队在街上欢迎我们。下午3时开 营以上政治十部会议，5时开联欢大会， 一师政治部表演 新 剧 。\n\n\n1 0 月 2 4 日\n晴 。\n在隆德县之兴隆镇休息。十七师、十八师方面发 现敌人，接触半小时，结果敌人退却。\n\n1 0 月 2 5 日\n晴。\n继续北进。凌晨4时半出发，经过40里，8时半到固 原县之硝河城宿营。9时敌机来一次，11时半敌机又 来 一 次 。\n\n1 0 月 2 6 日\n晴。\n准备午前5时出发，后改了命令，在硝河城休息一 天。敌机来了一次。\n\n1 0 月 2 7 日\n晴。\n凌晨4时出发，经过30里，7时半到达木家营，刚到 房子一小时许，敌机来了，投弹二颗。前面十几里的地方 发生剧烈的机关枪声，是二军四师与敌人遭遇，结果 枪声渐稀，敌人败退。下午3时继续出发，经过30里，时至 9点钟了，即宿营于船儿湾。\n\n1 0 月 2 8 日\n晴。\n凌晨4时出发，经过约30余里，8时半到达洪家庄 (张玄铺)宿营。\n\n\n1 0 月 2 9 日\n晴。\n上午5时出发，坚决通过海原与黑城之问的封锁线，进入陕甘宁苏区。本来上午到槽家湾大休息，下午继 续行进40里，但因槽家湾到达了敌人，同时我们行军的 左右都遭遇敌人，并且敌机来得厉害， 一连来一二架、三 四架，继续一天轰炸到日下山才停止，故未到槽家湾大休 息， 一直通过封锁线到乡土庄宿营。\n\n1 0 月 3 1 日\n晴。\n30日凌晨1时出发，实行夜行军，到达△△宿营；下 午3时继续行军，到31日凌晨一二时才宿营于△△。\n\n1 1 月 1 日\n由 3 1 日宿营地前进10里，到陈家湾。此地驻了一方 面军十五军团的队伍，没有房子，我们即与他们挤在 一起，休息半天，他们出发去作战，我们下午3时继续出 发，将到东家铺子时遭遇敌机，向我们投弹10余颗，幸我 军疏开隐蔽很快，未受到大的伤亡。是日即在东家铺子宿 营。\n\n\n1 1 月 2 日\n晴。\n凌晨4时出发，本来到关桥堡休息整理，因关桥堡驻 了三十一军,故我们即在海家湾。\n\n\n1 1 月 3 日\n晴。\n部队由海家湾开往双和铺。我与他们去二方面军总指挥部开会，下午5时开会，朱总司令报告党中央关于  集中一、二、四方面军，消灭胡宗南部的战争动员问  题。本来我军在双和铺一线有相当时间休息整理，但因战  争环境紧张，故加紧战争准备工作，没有得到什么休息。\n\n1 1 月 4 日\n晴。\n上午5时半由方总(何家堡)倒回双和铺。\n\n\n1 1 月 5 日\n晴。\n凌晨4时出发，准备消灭胡敌。我军配合一、四方 面军战斗动作，为战斗后备队。上午9时到达上马营，后 又打转宿营于下马营。是日夜晚下大雪，奇寒，比之南方 12月还冷得厉害。\n\n\n1 1 月 6 日\n晴。\n上午5时半由下马营出发，转回双和铺。因双和铺驻 了方总，我军即在离双和铺六七里的杨家湾一线集结，推 备参加战斗，消灭胡敌。\n\n1 1 月 7 日\n晴。\n即在离双和铺六七里的地方集结隐蔽，准备消灭胡 敌。\n\n1 1 月 8 日\n晴。\n因胡敌不敢速进，司时集结其主力构筑工事，因此没 有进行消灭胡敌的战斗，我军即转移新的地区。凌晨4时 出发，经过老虎沟、罗家要险、羊家要险，到达牛龙川宿 营。\n\n\n1 1 月 9 日\n晴。\n上午5时，本来到李旺堡，后到木家田庄宿营。此地 驻了十五军团教导队及二方面军政治部。\n\n1 1 月 1 0 日\n晴。\n上午在木家田庄休息，下午3时出发，只走10来里， 即打转几里到蔡家塔宿营。\n\n1 1 月 1 1 日\n晴。\n本来继续向预旺堡前进，因彭（彭德怀）命令一、四方面军准备消灭东进的胡敌，我军亦要参加战斗，故凌晨4时半 出发，到达工家田庄。休息了半天，因未进行战斗，所以我 军继续向预旺堡前进，下午4时出发，本来到关田宿营， 因天色晚了，夜行军冷，只走10来里路即宿营。\n\n11 月 1 2 日\n晴。\n上午5时出发，将到阁家瑶时遭遇敌机，投弹数颗， 我伤亡数名。在阁家瑶大休息，下午3时继续前进，8时到  达预旺堡宿营。\n\n1 1 月 1 3 日\n晴。\n本来可以在预旺堡休息，因东北军后日即可从预 旺堡经过，我们部队在预旺堡太多，如我军在预旺堡休息 一天，则东北军经过时，我们拥挤不好移动，故上午5时 半出发，到油房塘的王家园宿营。\n\n1 1 月 1 4 日\n晴。\n上午5时出发，下午1时到达毛居井宿营。\n\n\n1 1 月 1 5 日\n晴。\n上午5时出发，下午1时半到达毛家川(小地名杨房\n子)宿营。\n\n\n1 1 月 1 6 日\n晴。\n上午5时出发，前进约七八里，全军集合，由王政委 训话。后继续前进，到胡家湾大休息。下午3时继续前进， 7时半到达三龙殿。\n\n\n1 1 月 1 8 日\n晴 。\n17口在三龙殿休息。在三龙殿本来有相当休息的时 间，因胡敌继续东进，我军要配合一、四方面军消灭胡敌，故又继续行动。是日下午4时出发，9时到达新集子一线 宿营。\n\n1 1 月 1 9 日\n晴 。\n在新集子一线集结备战，同时，是我二方面军突围远 征的周年纪念日，每人增加一角钱，举行会餐与晚会，以 资纪念。\n\n1 1 月 2 0 日\n晴。\n（一）因敌情没有起什么变化，仍在新集子一线集结 备战；(二)根据政治委员意见，起草关于消灭胡敌战 争动员的报告大纲。\n\n1 1 月 2 1 日\n晴。\n(一)上午7时由新集子出发，转移于船林沟的庙家 庄，只走七里路，到雇家庄约一二小时，飞机来了一次；\n(二)上改治课，讲党中央关于抗日救亡运动新形势与民主共和国的决议(一至四段);(三)晚上记录政治委员口 述关干目前环境下政治工作任务。\n\n1 1 月 2 2 日\n晴。\n仍在庙家庄。(一)上午整理政治委员口述关于目前 环境下政治工作任务；(二)下午又上政治课，材料同上 (讲五至七段);(三)晚上参加政治部谈话会。\n\n1 1 月 2 3 日\n晴。\n仍在庙家庄。(一)上午上政治课，讲完同上材料(八 至十段);(二)听政治委员确定部队目前的政治工作，分  配我写红读（红军战士读本）一册问答、新形势与新策略讨论提纲； (三)参加政治部全军指导员、支部书记以上政治干部与 团长的会议。\n\n1 1 月 2 4 日\n晴。\n(一)上午5时出发，向何连湾转移，虽只30余里，然因我病后体力尚未恢复，行走时犹觉遥遥很远。(二)离何连湾一里多路时，因宿营地没有弄清，故向何连湾前进 了，又打转停止。在停止的中间，敌机来了，敌机飞远了一 点，喊走，随即敌机飞近了，又喊停止，如此动作数次，结 果到何连湾宿营。刚到何连湾敌机又来了，并投弹于何连 湾附近地方。(三)何连湾有陕甘宁省委、省苏等机关， 并驻了方面军直属队一部分机关，如供给部。\n\n1 1 月 2 5 日\n晴。\n(一)本来今天上午没有出发，下午无论如何要出发， 但得方面军首长决心改本军明日(26日)出发，因此得到  在何连湾休息一天。部队积极准备七天粮食和二天干粮， 继续三天行军，进到羊圈山，准备战斗。(二)敌机只在日  头出山一丈高时(7点钟)来了，在我们驻地绕了数次但未  丢弹，只打轻机关枪。(三)因我们有新的任务，全方面军  参谋人员到新集子一线侦察地形。\n\n1 1 月 2 6 日\n晴。\n\n〔1〕陕甘宁省委、省苏  1936年5月 1 7 日，根据中共中央决定，中共 陕甘省委撤销，成立中共陕甘宁省委，李富春任书记；同时，成立陕甘宁省苏 维埃，简称省苏，马锡五任主席，我二方面军为突击队，去迎击毛以哲之第三师与 一零八师(他们要经二十里铺进入环县,凌晨3时出 发，8时到达李家院(离三龙殴七里),后转到胡家院集结 隐蔽，待机作战。但是敌人咋天受了我八十一师的打 击(缴获其五六挺机关枪，打死其500多匹马),不敢速 进，故战争没有打响，而由胡家院转到李家院宿营。\n\n1 1 月 2 7 日\n晴。\n因敌人知道我军伏击、侧击其意图，继续与敌人作战 是不利的，故凌晨3时出发，转回何迕湾。\n\n1 1 月 2 8 日\n晴。\n继续去侧击东北军之一师。凌晨3时出发，8时到达 黑家院，稍微休息一下，即赶到庄家院野外并与八十一师 取好了联络，隐蔽集结，准备作战，但等了四五点钟，敌人 尚没有来，战争又没有打响。各部队吃完饭后，下午3时 又转回何连湾。\n\n1 1 月 2 9 日\n得接总指挥部的命令，本军在何连湾有七天休息。因 胡敌在甜水堡、惠安堡休息筹粮，故本军在何连湾。\n\n1 1 月 3 0 日\n晴。\n方面军政治部通知，下午1时开方面军的活动分子 会议。中午饭后我也去参加此会，下乍7时才开会，首先 甘主任报告整理训练部队的工作，继则一军团政治部 主任朱瑞同志补充整理训练工作一些意见及一方面军的 工作经验，约12时才散会、睡觉。\n\n1 2 月 1 日\n晴。\n仍在方面军政治部开会。上午8时至9时各军到会同 志讨论各军的整训工作。上午10时，开全方面军的活动 分子会，张浩同志报告国际消息，传达第七次世界大会（共产国际第七次代表大会）的总结，报告到下午4时半才结束。\n\n\n1 2 月 2 日\n晴。\n任政治委员报告长征的总结,从上午9时起，报 告到下乍7时止，中间休息吃饭约两小时。任政治委员报 告后，有国际代表张浩同志、总指挥贺龙同志、六军团政 委王震同志、方面军政治部主任甘泗淇同志发言。会议至 今天结束了。\n\n1 2 月 3 日\n晴。\n我从方面军政治部(庙咀子)转回六军团政治部(何 连湾)。\n\n1 2 月 4 日\n晴。\n胡敌有继续进攻盐池的企图。我们为了随时准备 消灭敌人，向黑城岔以南李家大湾转移。下午1时出发， 经过洪德城、庙咀子，7时到达李家大湾之崔家院子宿营。 行程30余里。\n\n1 2 月 5 日\n晴。\n上午12时由崔家院出发，经过黑城岔，下午5时半到 达刘家拐沟以南之康家庄宿营。行程40余里。\n\n1 2 月 6 日\n晴。\n上午10时出发，经过刘家拐沟，下午5时半进到谢家 土洞以南之庙家咀子宿营。行程50余里。\n\n1 2 月 7 日\n晴。\n下午2时向姜家台移动，经过五六里，3时到达姜家 台之苗家大渠，离谢家土洞二三里，离定边1〕城140里， 离盐池城120里。此地系陕北定边县地区。\n\n1 2 月 1 2 日\n晴。\n8至12日均在苗家大渠，待机备战。\n\n\n1 2 月 1 3 日\n晴。\n仍在姜家台之苗家大渠。早晨7时得接红中社23、 中央军委电讯：西安事变,爱国将军张学良，杨虎城在 全国与西安革命势力推动下，捕捉了卖国贼头子蒋介石及其走狗陈诚、陈继承、蒋鼎文、朱绍 良、卫立煌、钱大钧等六人，打死蒋孝先、邵 元 冲 及宪兵团团长，打伤钱大钧，解除了宪兵团及驻 西安的中央军、警察等武装，俘虏了随蒋来西安的全部南 京中央委员，开展了中国革命新的阶段。这一胜利消息传 来，使我从来没有这样兴奋。\n\n\n1 2 月 1 4 日\n晴。\n由于西安事变，胡宗南部正向西退，使我们担负待机 备战消灭胡敌的任务，转入准备新的战略行动，加紧部队 整理训练。故总部〔10〕来电，要我们仍在原地休息整理，准备新的行动的工作。\n\n\n1 2 月 1 5 日\n晴。\n上午在苗家大渠。下午2时，全军团以上干部去深田 子参加全方面军积极分子会议。这一会议，首先由关政 委宣布开会，继由朱主任2报告西安事变的经过、原 因、政治意义、发展前途、我们的任务、中心工作、行动中 应注意的事项，再则甘主任发言，散会。散会时已天 黑。因为明天要行动，即连夜赶回苗家人渠军部。\n\n1 2 月 1 6 日\n晴。\n早晨下大霜，好象落了雪一样。木来出发，并在6时 准备完结，向环县、庆阳、西峰城南移，配合东北抗 日友军作战，刚要出发时，接总指挥部来的命令，暂时停 止行动，加紧筹足10天以上的粮食，改变行动路线，准备向甘泉前进，经过保安、肤施等地，去配合东北 抗日友军，故仍在苗家大渠休息。\n\n\n1 2 月 1 7 日\n晴。\n早晨同样下大霜。上午6时准备完毕，6时半出发，经 过姬家园，集结部队，工政委讲话，说明西安事变的经过 及我们的任务。下午4时到达西庄园宿营。\n\n1 2 月 1 8 日\n晴。\n上午6时出发，经过罗儿要险，这一路都驻了后方机 关。下午5时到达离铁边城 30里之黑溪曲儿宿营。\n\n1 2 月 1 9 日\n晴。\n下了一点雪。上午6时半出发，经过铁边城，本来要  超过铁边城40里以东地区宿营，但在超过铁边城15里之  杨家庙台，得接方总骑兵送来军委命令，二方面军19日  即在原地停止休息，改变前进路线，向西峰镇前进。因此， 我们即在杨家庙台宿营。\n\n\n1 2 月 2 0 日\n晴。\n上午在杨家庙台休息。下午得接命令向南行动，2时 半出发，5时半到达南庄板宿营.\n\n1 2 月 2 1 日\n雪。\n继续向南前进。上午6时出发，经过杜家大岔、吕沟 咀，到达离元城镇12里东北地区之宋家店房宿营，与陕 廿宁省保卫局驻在一起。\n\n\n1 2 月 2 2 日\n晴。\n总指挥（贺龙）来的指示：加紧部队的整理工作，准备二天行军，到达庆阳东南地区停止。上午7时30分出发，经 过元城子，全军集合(缺五十三团),王政委讲话。后继续 南进，下午3时到达杜家右手宿营。\n\n1 2 月 2 3 日\n晴。\n上午7时半出发，经过70里，下午3时半到达悦乐上铺子宿营。\n\n\n1 2 月 2 4 日\n阴。\n向庆阳前进。上午7时出发，下午3时到达离庆阳20 里以北地区之贾家桥宿营。\n\n1 2 月 2 5 日\n晴。\n本来总指挥部来信，要进到左家岗山十里铺去，但夜 间来信决定在贾家桥休息一天。\n\n1 2 月 2 6 日\n晴。\n仍在贾家桥休息。\n\n\n1 2 月 2 7 日\n晴。\n上午7时半出发，下午1时半到达十里铺之刘家院了 宿营。陈军长、张主任均由红大回来。\n\n1 2 月 2 8 日\n晴。\n总指挥部来的指示，本军须在原地停止，待命行动。 因此，我们就在十里铺过来五里之刘家院子休息  天 。\n\n1 2 月 2 9 日\n晴。\n上午7时出发，向东前进，12时到达合水城，进城 时恰逢合水工作团召集样众会议，东北军一个副官在那 里讲演，我们听了一会儿才进房子。 这一回进城的特点，即是有东北军和县政府的存在，有旧的社会团体、各种机关的存在。\n\n\n1 2 月 3 0 日\n晴。\n在合水城休息。我由司令部转到政治部。前(11月10 日)由木家田庄到司令部，共一个月20天。\n\n1 2 月 3 1 日\n晴 。\n在合水休息。这是1936年最后的一天.政治部欢宴 东北军、县政府、商界、学界、各机关人员， 一方面辞别 1936年，迎接1937年，另  方面庆祝抗日统一战线的胜 利。欢宴席上有张、陈、王（张子意，陈伯钧、王震）",
      "weather": "晴",
      "char_count": 8205,
      "diary_id": "王恩茂日记",
      "diary_name": "《王恩茂日记》——红军长征到“七七“事变前夕",
      "diary_index": 1
    },
    {
      "date_raw": "9 月 9 日",
      "year": 1937,
      "month": 9,
      "day": 9,
      "text": "上午6时由崖湾里转移于岩村。\n\n\n9 月 1 0 日\n阴 。\n在岩村休息。\n\n9 月 1 1 日\n上午雨，下午阴。\n凌晨1时出发，经过马家河、枣下河，翻了三个小小 的山，下午5时半到达永坪镇。\n\n\n9 月 1 2 日\n晴 。\n上午在永坪镇休息，12时出发，向天水镇  前进，下 个7时半到达横河镇宿营。\n\n9 月 1 3 日\n上午阴，下午雨。\n在横河镇休息。\n\n\n9 月 1 4 日\n上午雨，下午阴。\n上午在横河镇休息，下午1时出发，经过草坝，6时到 达余家坪(小地名赵家崖湾里)宿营。\n\n9 月 1 5 日\n晴。\n上车5时半出发，本米军直与模范师、十八师为左纵 队，经寻家底到达天水镇宿营，十七师与十六师经罗家铺取道至天水镇，但因天水镇有敌，故至平南川宿营。\n\n\n9 月 1 6 日\n晴。\n本军担任夺取两当县城的任务。凌晨4时出发， 向两当县城前进，经过张家峪、娘娘坝，到骆驼上大休息。 到李子园，前卫部队消灭卖国匪军一个连，缴获步枪10 余支。下午7时到达百纳峡宿营。\n\n9 月 1 7 日\n晴。\n上午6时出发，经过高桥、白杨林等地，下午6时平， 到达徽县之马家庄宿营。\n\n9 月 1 8 日\n晴。\n凌晨3时半出发，经过韩家湾，继续翻过两个山，下 午1时到达两当县城。我先头部队拂晓攻城，守城之敌全 末为之防，被我军全部消灭，缴获步枪数十支、连枪一支、收音机一架，俘获县政府全部工作人员。是口早出发时， 王政委报告：二军之  部占领成县,击溃毛炳 文一个团，缴获步枪300余支。\n\n9 月 1 9 日\n晴。\n为完成拿下凤县之任务，未在两当城休息，仍继 续向风县前进。上午5时出发，经过杨家店子、双石铺，下 午4时到达离凤城四五里的地方，模范师在攻城，但木攻 克，即在桑园宿营。\n\n\n9 月 2 0 日\n晴 。\n上午在桑园休息，下午撤凤县之围，6时出发，退回双 石铺宿营。\n\n\n9 月 2 1 日\n晴。\n上午在双石铺休息，下个敌机向双石铺旋绕数次。下 午1时出发，回两当、徽县工作，但因走到杨家店天即快 黑了，故即在杨家店宿营。\n\n9 月 2 2 日\n晴 。\n上午6时出发，经过灵官殿，下午9时到达两当城。\n\n9 月 2 9 日\n从23日起到29日均在两当城。\n\n\n9 月 3 0 日\n雨。\n由两当到杨家店检查突击扩红工作。\n\n\n1 0 月 3 日\n1日至3日均在杨家店参加突击扩红工作。\n\n\n1 0 月 4 日\n晴。\n凌晨1时由杨家店出发，天未亮即抵两当城，休息一二小时，继续前进，到达马家庄宿营。\n\n\n1 0 月 5 日\n晴。\n上午5时出发，经过白杨林、高桥等地，到达百纳峡 乂前进25里，下午9时才到李子园宿营。\n\n1 0 月 6 日\n晴。\n为了通过天水、徽县、成县敌人的封锁线，迅速与一 方面军会合，故夜行军。凌晨1时出发，经过大门镇，下午 4时到达杨家湾宿营。\n\n1 0 月 7 日\n上午阴，下午雨。\n凌晨3时出发，向横河镇前进，沿途敌人打枪，特别 是经过罗家堡时，因敌机轰炸，配合陆军动作，同时十六 师压制松懈，致使敌人出击。军直、模范师均从敌人枪林 弹雨中冲出来，下午4时半到达横河镇宿营。\n\n1 0 月 8 日\n阴。\n凌晨4时出发，下午1时到达固城附近宿营。\n\n\n1 0 月 9 日\n晴。\n为了北渡渭水，通过陕甘大道与一、四方面军会合， 凌晨3时出发，沿途休息多次，下午八九时到达五十里 铺，即渡河到达甘谷县之永安乡宿营。\n\n1 0 月 1 0 日\n雨。\n在永安休息。\n\n\n1 0 月 1 1 日\n晴。\n上午5时出发，向礼辛镇前进，沿途遭遇敌机，敌机 往返五六次，投弹五六十颗，这是我们进入甘肃遇到敌机 轰炸最厉害的一回。因为隐蔽敌机的原故，下午4时许才到礼辛镇宿营。\n\n\n1 0 月 1 2 日\n晴。\n为了避免敌机轰炸，决定夜行军，凌晨1时出发，本 来到李家店子，因走错了路到常河镇即日出几尺了，故即 在常河镇宿营。\n\n1 0 月 1 3 日\n晴。\n凌晨零时30分出发，天亮到达马家店子休息大半 天。下午3时继续出发，夜行军到通渭县之吴家村宿 营。吴家村离通渭10里。\n\n\n1 0 月 1 4 日\n晴。\n在吴家村休息大半天，下午3时出发，夜行军，经过 50里，12时到达蔡家镇宿营。\n\n1 0 月 1 6 日\n晴。\n15、16日均在蔡家镇休息。\n\n\n1 0 月 1 7 日\n晴。\n凌晨3时出发，经过40里，8时到达四沟河(寺咀 镇)。为了迅速与一方面军会合，下午3时继续行军，经过 60里到青家驿。本来即在该地宿营，但因驻了九军部队， 我们停留了好久，正是半夜，冷得厉害，又没房子宿营，要 再走20里才有房了，故即挤在九军驻的房子内宿营。\n\n1 0 月 1 8 日\n晴。\n天亮木吃早饭即出发，上午9时许到达老君铺。 一方 面军二师派了五团一部分同志来欢迎我们。\n\n10月 1 9 日\n晴.。\n在老君铺，早晨集合，十六师、十八师、模范师全部及 十七师连以上干部，欢迎红五团参观代表，请红五团  政委报告陕北苏区情况和反帝统一战线的伟大胜利。\n\n1 0 月 2 1 日\n晴。\n20、21日均在老君铺休息。\n\n1 0 月 2 2 日\n晴。\n原命令向南贻河前进，后改向公阳镇前进，经过70 里到达该地宿营。该地都是回民居住。\n\n1 0 月 2 3 日\n晴。\n凌晨4时出发，天亮即到兴隆镇,与一方面军一 军团一师会合， 一师直属队在街上欢迎我们。下午3时开 营以上政治十部会议，5时开联欢大会， 一师政治部表演 新 剧 。\n\n\n1 0 月 2 4 日\n晴 。\n在隆德县之兴隆镇休息。十七师、十八师方面发 现敌人，接触半小时，结果敌人退却。\n\n1 0 月 2 5 日\n晴。\n继续北进。凌晨4时半出发，经过40里，8时半到固 原县之硝河城宿营。9时敌机来一次，11时半敌机又 来 一 次 。\n\n1 0 月 2 6 日\n晴。\n准备午前5时出发，后改了命令，在硝河城休息一 天。敌机来了一次。\n\n1 0 月 2 7 日\n晴。\n凌晨4时出发，经过30里，7时半到达木家营，刚到 房子一小时许，敌机来了，投弹二颗。前面十几里的地方 发生剧烈的机关枪声，是二军四师与敌人遭遇，结果 枪声渐稀，敌人败退。下午3时继续出发，经过30里，时至 9点钟了，即宿营于船儿湾。\n\n1 0 月 2 8 日\n晴。\n凌晨4时出发，经过约30余里，8时半到达洪家庄 (张玄铺)宿营。\n\n\n1 0 月 2 9 日\n晴。\n上午5时出发，坚决通过海原与黑城之问的封锁线，进入陕甘宁苏区。本来上午到槽家湾大休息，下午继 续行进40里，但因槽家湾到达了敌人，同时我们行军的 左右都遭遇敌人，并且敌机来得厉害， 一连来一二架、三 四架，继续一天轰炸到日下山才停止，故未到槽家湾大休 息， 一直通过封锁线到乡土庄宿营。\n\n1 0 月 3 1 日\n晴。\n30日凌晨1时出发，实行夜行军，到达△△宿营；下 午3时继续行军，到31日凌晨一二时才宿营于△△。\n\n1 1 月 1 日\n由 3 1 日宿营地前进10里，到陈家湾。此地驻了一方 面军十五军团的队伍，没有房子，我们即与他们挤在 一起，休息半天，他们出发去作战，我们下午3时继续出 发，将到东家铺子时遭遇敌机，向我们投弹10余颗，幸我 军疏开隐蔽很快，未受到大的伤亡。是日即在东家铺子宿 营。\n\n\n1 1 月 2 日\n晴。\n凌晨4时出发，本来到关桥堡休息整理，因关桥堡驻 了三十一军,故我们即在海家湾。\n\n\n1 1 月 3 日\n晴。\n部队由海家湾开往双和铺。我与他们去二方面军总指挥部开会，下午5时开会，朱总司令报告党中央关于  集中一、二、四方面军，消灭胡宗南部的战争动员问  题。本来我军在双和铺一线有相当时间休息整理，但因战  争环境紧张，故加紧战争准备工作，没有得到什么休息。\n\n1 1 月 4 日\n晴。\n上午5时半由方总(何家堡)倒回双和铺。\n\n\n1 1 月 5 日\n晴。\n凌晨4时出发，准备消灭胡敌。我军配合一、四方 面军战斗动作，为战斗后备队。上午9时到达上马营，后 又打转宿营于下马营。是日夜晚下大雪，奇寒，比之南方 12月还冷得厉害。\n\n\n1 1 月 6 日\n晴。\n上午5时半由下马营出发，转回双和铺。因双和铺驻 了方总，我军即在离双和铺六七里的杨家湾一线集结，推 备参加战斗，消灭胡敌。\n\n1 1 月 7 日\n晴。\n即在离双和铺六七里的地方集结隐蔽，准备消灭胡 敌。\n\n1 1 月 8 日\n晴。\n因胡敌不敢速进，司时集结其主力构筑工事，因此没 有进行消灭胡敌的战斗，我军即转移新的地区。凌晨4时 出发，经过老虎沟、罗家要险、羊家要险，到达牛龙川宿 营。\n\n\n1 1 月 9 日\n晴。\n上午5时，本来到李旺堡，后到木家田庄宿营。此地 驻了十五军团教导队及二方面军政治部。\n\n1 1 月 1 0 日\n晴。\n上午在木家田庄休息，下午3时出发，只走10来里， 即打转几里到蔡家塔宿营。\n\n1 1 月 1 1 日\n晴。\n本来继续向预旺堡前进，因彭（彭德怀）命令一、四方面军准备消灭东进的胡敌，我军亦要参加战斗，故凌晨4时半 出发，到达工家田庄。休息了半天，因未进行战斗，所以我 军继续向预旺堡前进，下午4时出发，本来到关田宿营， 因天色晚了，夜行军冷，只走10来里路即宿营。\n\n11 月 1 2 日\n晴。\n上午5时出发，将到阁家瑶时遭遇敌机，投弹数颗， 我伤亡数名。在阁家瑶大休息，下午3时继续前进，8时到  达预旺堡宿营。\n\n1 1 月 1 3 日\n晴。\n本来可以在预旺堡休息，因东北军后日即可从预 旺堡经过，我们部队在预旺堡太多，如我军在预旺堡休息 一天，则东北军经过时，我们拥挤不好移动，故上午5时 半出发，到油房塘的王家园宿营。\n\n1 1 月 1 4 日\n晴。\n上午5时出发，下午1时到达毛居井宿营。\n\n\n1 1 月 1 5 日\n晴。\n上午5时出发，下午1时半到达毛家川(小地名杨房\n子)宿营。\n\n\n1 1 月 1 6 日\n晴。\n上午5时出发，前进约七八里，全军集合，由王政委 训话。后继续前进，到胡家湾大休息。下午3时继续前进， 7时半到达三龙殿。\n\n\n1 1 月 1 8 日\n晴 。\n17口在三龙殿休息。在三龙殿本来有相当休息的时 间，因胡敌继续东进，我军要配合一、四方面军消灭胡敌，故又继续行动。是日下午4时出发，9时到达新集子一线 宿营。\n\n1 1 月 1 9 日\n晴 。\n在新集子一线集结备战，同时，是我二方面军突围远 征的周年纪念日，每人增加一角钱，举行会餐与晚会，以 资纪念。\n\n1 1 月 2 0 日\n晴。\n（一）因敌情没有起什么变化，仍在新集子一线集结 备战；(二)根据政治委员意见，起草关于消灭胡敌战 争动员的报告大纲。\n\n1 1 月 2 1 日\n晴。\n(一)上午7时由新集子出发，转移于船林沟的庙家 庄，只走七里路，到雇家庄约一二小时，飞机来了一次；\n(二)上改治课，讲党中央关于抗日救亡运动新形势与民主共和国的决议(一至四段);(三)晚上记录政治委员口 述关干目前环境下政治工作任务。\n\n1 1 月 2 2 日\n晴。\n仍在庙家庄。(一)上午整理政治委员口述关于目前 环境下政治工作任务；(二)下午又上政治课，材料同上 (讲五至七段);(三)晚上参加政治部谈话会。\n\n1 1 月 2 3 日\n晴。\n仍在庙家庄。(一)上午上政治课，讲完同上材料(八 至十段);(二)听政治委员确定部队目前的政治工作，分  配我写红读（红军战士读本）一册问答、新形势与新策略讨论提纲； (三)参加政治部全军指导员、支部书记以上政治干部与 团长的会议。\n\n1 1 月 2 4 日\n晴。\n(一)上午5时出发，向何连湾转移，虽只30余里，然因我病后体力尚未恢复，行走时犹觉遥遥很远。(二)离何连湾一里多路时，因宿营地没有弄清，故向何连湾前进 了，又打转停止。在停止的中间，敌机来了，敌机飞远了一 点，喊走，随即敌机飞近了，又喊停止，如此动作数次，结 果到何连湾宿营。刚到何连湾敌机又来了，并投弹于何连 湾附近地方。(三)何连湾有陕甘宁省委、省苏等机关， 并驻了方面军直属队一部分机关，如供给部。\n\n1 1 月 2 5 日\n晴。\n(一)本来今天上午没有出发，下午无论如何要出发， 但得方面军首长决心改本军明日(26日)出发，因此得到  在何连湾休息一天。部队积极准备七天粮食和二天干粮， 继续三天行军，进到羊圈山，准备战斗。(二)敌机只在日  头出山一丈高时(7点钟)来了，在我们驻地绕了数次但未  丢弹，只打轻机关枪。(三)因我们有新的任务，全方面军  参谋人员到新集子一线侦察地形。\n\n1 1 月 2 6 日\n晴。\n\n〔1〕陕甘宁省委、省苏  1936年5月 1 7 日，根据中共中央决定，中共 陕甘省委撤销，成立中共陕甘宁省委，李富春任书记；同时，成立陕甘宁省苏 维埃，简称省苏，马锡五任主席，我二方面军为突击队，去迎击毛以哲之第三师与 一零八师(他们要经二十里铺进入环县,凌晨3时出 发，8时到达李家院(离三龙殴七里),后转到胡家院集结 隐蔽，待机作战。但是敌人咋天受了我八十一师的打 击(缴获其五六挺机关枪，打死其500多匹马),不敢速 进，故战争没有打响，而由胡家院转到李家院宿营。\n\n1 1 月 2 7 日\n晴。\n因敌人知道我军伏击、侧击其意图，继续与敌人作战 是不利的，故凌晨3时出发，转回何迕湾。\n\n1 1 月 2 8 日\n晴。\n继续去侧击东北军之一师。凌晨3时出发，8时到达 黑家院，稍微休息一下，即赶到庄家院野外并与八十一师 取好了联络，隐蔽集结，准备作战，但等了四五点钟，敌人 尚没有来，战争又没有打响。各部队吃完饭后，下午3时 又转回何连湾。\n\n1 1 月 2 9 日\n得接总指挥部的命令，本军在何连湾有七天休息。因 胡敌在甜水堡、惠安堡休息筹粮，故本军在何连湾。\n\n1 1 月 3 0 日\n晴。\n方面军政治部通知，下午1时开方面军的活动分子 会议。中午饭后我也去参加此会，下乍7时才开会，首先 甘主任报告整理训练部队的工作，继则一军团政治部 主任朱瑞同志补充整理训练工作一些意见及一方面军的 工作经验，约12时才散会、睡觉。\n\n1 2 月 1 日\n晴。\n仍在方面军政治部开会。上午8时至9时各军到会同 志讨论各军的整训工作。上午10时，开全方面军的活动 分子会，张浩同志报告国际消息，传达第七次世界大会（共产国际第七次代表大会）的总结，报告到下午4时半才结束。\n\n\n1 2 月 2 日\n晴。\n任政治委员报告长征的总结,从上午9时起，报 告到下乍7时止，中间休息吃饭约两小时。任政治委员报 告后，有国际代表张浩同志、总指挥贺龙同志、六军团政 委王震同志、方面军政治部主任甘泗淇同志发言。会议至 今天结束了。\n\n1 2 月 3 日\n晴。\n我从方面军政治部(庙咀子)转回六军团政治部(何 连湾)。\n\n1 2 月 4 日\n晴。\n胡敌有继续进攻盐池的企图。我们为了随时准备 消灭敌人，向黑城岔以南李家大湾转移。下午1时出发， 经过洪德城、庙咀子，7时到达李家大湾之崔家院子宿营。 行程30余里。\n\n1 2 月 5 日\n晴。\n上午12时由崔家院出发，经过黑城岔，下午5时半到 达刘家拐沟以南之康家庄宿营。行程40余里。\n\n1 2 月 6 日\n晴。\n上午10时出发，经过刘家拐沟，下午5时半进到谢家 土洞以南之庙家咀子宿营。行程50余里。\n\n1 2 月 7 日\n晴。\n下午2时向姜家台移动，经过五六里，3时到达姜家 台之苗家大渠，离谢家土洞二三里，离定边1〕城140里， 离盐池城120里。此地系陕北定边县地区。\n\n1 2 月 1 2 日\n晴。\n8至12日均在苗家大渠，待机备战。\n\n\n1 2 月 1 3 日\n晴。\n仍在姜家台之苗家大渠。早晨7时得接红中社23、 中央军委电讯：西安事变,爱国将军张学良，杨虎城在 全国与西安革命势力推动下，捕捉了卖国贼头子蒋介石及其走狗陈诚、陈继承、蒋鼎文、朱绍 良、卫立煌、钱大钧等六人，打死蒋孝先、邵 元 冲 及宪兵团团长，打伤钱大钧，解除了宪兵团及驻 西安的中央军、警察等武装，俘虏了随蒋来西安的全部南 京中央委员，开展了中国革命新的阶段。这一胜利消息传 来，使我从来没有这样兴奋。\n\n\n1 2 月 1 4 日\n晴。\n由于西安事变，胡宗南部正向西退，使我们担负待机 备战消灭胡敌的任务，转入准备新的战略行动，加紧部队 整理训练。故总部〔10〕来电，要我们仍在原地休息整理，准备新的行动的工作。\n\n\n1 2 月 1 5 日\n晴。\n上午在苗家大渠。下午2时，全军团以上干部去深田 子参加全方面军积极分子会议。这一会议，首先由关政 委宣布开会，继由朱主任2报告西安事变的经过、原 因、政治意义、发展前途、我们的任务、中心工作、行动中 应注意的事项，再则甘主任发言，散会。散会时已天 黑。因为明天要行动，即连夜赶回苗家人渠军部。\n\n1 2 月 1 6 日\n晴。\n早晨下大霜，好象落了雪一样。木来出发，并在6时 准备完结，向环县、庆阳、西峰城南移，配合东北抗 日友军作战，刚要出发时，接总指挥部来的命令，暂时停 止行动，加紧筹足10天以上的粮食，改变行动路线，准备向甘泉前进，经过保安、肤施等地，去配合东北 抗日友军，故仍在苗家大渠休息。\n\n\n1 2 月 1 7 日\n晴。\n早晨同样下大霜。上午6时准备完毕，6时半出发，经 过姬家园，集结部队，工政委讲话，说明西安事变的经过 及我们的任务。下午4时到达西庄园宿营。\n\n1 2 月 1 8 日\n晴。\n上午6时出发，经过罗儿要险，这一路都驻了后方机 关。下午5时到达离铁边城 30里之黑溪曲儿宿营。\n\n1 2 月 1 9 日\n晴。\n下了一点雪。上午6时半出发，经过铁边城，本来要  超过铁边城40里以东地区宿营，但在超过铁边城15里之  杨家庙台，得接方总骑兵送来军委命令，二方面军19日  即在原地停止休息，改变前进路线，向西峰镇前进。因此， 我们即在杨家庙台宿营。\n\n\n1 2 月 2 0 日\n晴。\n上午在杨家庙台休息。下午得接命令向南行动，2时 半出发，5时半到达南庄板宿营.\n\n1 2 月 2 1 日\n雪。\n继续向南前进。上午6时出发，经过杜家大岔、吕沟 咀，到达离元城镇12里东北地区之宋家店房宿营，与陕 廿宁省保卫局驻在一起。\n\n\n1 2 月 2 2 日\n晴。\n总指挥（贺龙）来的指示：加紧部队的整理工作，准备二天行军，到达庆阳东南地区停止。上午7时30分出发，经 过元城子，全军集合(缺五十三团),王政委讲话。后继续 南进，下午3时到达杜家右手宿营。\n\n1 2 月 2 3 日\n晴。\n上午7时半出发，经过70里，下午3时半到达悦乐上铺子宿营。\n\n\n1 2 月 2 4 日\n阴。\n向庆阳前进。上午7时出发，下午3时到达离庆阳20 里以北地区之贾家桥宿营。\n\n1 2 月 2 5 日\n晴。\n本来总指挥部来信，要进到左家岗山十里铺去，但夜 间来信决定在贾家桥休息一天。\n\n1 2 月 2 6 日\n晴。\n仍在贾家桥休息。\n\n\n1 2 月 2 7 日\n晴。\n上午7时半出发，下午1时半到达十里铺之刘家院了 宿营。陈军长、张主任均由红大回来。\n\n1 2 月 2 8 日\n晴。\n总指挥部来的指示，本军须在原地停止，待命行动。 因此，我们就在十里铺过来五里之刘家院子休息  天 。\n\n1 2 月 2 9 日\n晴。\n上午7时出发，向东前进，12时到达合水城，进城 时恰逢合水工作团召集样众会议，东北军一个副官在那 里讲演，我们听了一会儿才进房子。 这一回进城的特点，即是有东北军和县政府的存在，有旧的社会团体、各种机关的存在。\n\n\n1 2 月 3 0 日\n晴。\n在合水城休息。我由司令部转到政治部。前(11月10 日)由木家田庄到司令部，共一个月20天。\n\n1 2 月 3 1 日\n晴 。\n在合水休息。这是1936年最后的一天.政治部欢宴 东北军、县政府、商界、学界、各机关人员， 一方面辞别 1936年，迎接1937年，另  方面庆祝抗日统一战线的胜 利。欢宴席上有张、陈、王（张子意，陈伯钧、王震）",
      "weather": "晴",
      "char_count": 8205,
      "diary_id": "王恩茂日记",
      "diary_name": "《王恩茂日记》——红军长征到“七七“事变前夕",
      "diary_index": 1
    },
    {
      "date_raw": "1 月 1 日",
      "year": 1937,
      "month": 1,
      "day": 1,
      "text": "新年节。晴。\n在合水过年。上午9时参加干部会议，张主任报告指 出；1937年是中国抗战的一年，是中华民族生命转变的一 年；罪恶的内战随着1936年结束而结束，光荣的抗战随 着1937年开始而开始。继续有陈军长、王政委讲话。会议 结束，会餐、摄影，随后打篮球、打乒乓球。下午5时，县政 府请吃饭。今年过新年的特点；(1)过去的新年都是处在 成斗环境中，而今年却在有利时机整理休息中过年；(2) 今年过年不仅有指战员的同乐，而且与合水县各界与东 北军联欢；(3)过去的新年都是在南方，今年却在抗日的 西 北 ，",
      "weather": "",
      "char_count": 253,
      "diary_id": "王恩茂日记",
      "diary_name": "《王恩茂日记》——红军长征到“七七“事变前夕",
      "diary_index": 1
    },
    {
      "date_raw": "1 月 2 日",
      "year": 1937,
      "month": 1,
      "day": 2,
      "text": "仍在合水城休息，上个9时参加全军庆祝新年同尔 大会。本来这个会是在1日开的，因1日干部会议、会餐、 摄影、同乐，没有时间，故延到2日才开。",
      "weather": "晴",
      "char_count": 69,
      "diary_id": "王恩茂日记",
      "diary_name": "《王恩茂日记》——红军长征到“七七“事变前夕",
      "diary_index": 1
    },
    {
      "date_raw": "1 月 3 日",
      "year": 1937,
      "month": 1,
      "day": 3,
      "text": "仍在合水休息。",
      "weather": "晴",
      "char_count": 7,
      "diary_id": "王恩茂日记",
      "diary_name": "《王恩茂日记》——红军长征到“七七“事变前夕",
      "diary_index": 1
    },
    {
      "date_raw": "1 月 4 日",
      "year": 1937,
      "month": 1,
      "day": 4,
      "text": "因为形势的变化，南京亲日派扣留张学良,蒋介 石撤退陕甘之军队被何应钦又复调集潼关,内 战风云紧张。我们为贯彻“停止内战， 一致抗日”的主张， 故继续南下，准备配合抗日友军 - — 东北军、十七路 军打击亲日派军队。上午6时半出发，经过西华池，到 达朱家寨子宿营。走了90里，",
      "weather": "阴",
      "char_count": 137,
      "diary_id": "王恩茂日记",
      "diary_name": "《王恩茂日记》——红军长征到“七七“事变前夕",
      "diary_index": 1
    },
    {
      "date_raw": "1 月 5 日",
      "year": 1937,
      "month": 1,
      "day": 5,
      "text": "上午6时半出发，经过南义井，下午1时半到达宁 县宿营，走了60里。宁县旧的机关均照原样存在，并 有保安队100余人。",
      "weather": "阴",
      "char_count": 58,
      "diary_id": "王恩茂日记",
      "diary_name": "《王恩茂日记》——红军长征到“七七“事变前夕",
      "diary_index": 1
    },
    {
      "date_raw": "1 月 6 日",
      "year": 1937,
      "month": 1,
      "day": 6,
      "text": "早晨雾，下午出了一点太阳。\n上午6时半出发，经过早胜镇、宫河镇，到达正宁 县附近之长口子宿营，走了90里。",
      "weather": "",
      "char_count": 53,
      "diary_id": "王恩茂日记",
      "diary_name": "《王恩茂日记》——红军长征到“七七“事变前夕",
      "diary_index": 1
    },
    {
      "date_raw": "1 月 7 日",
      "year": 1937,
      "month": 1,
      "day": 7,
      "text": "上午7时出发，经过店子河(原系关中苏区)、大 峪镇，到达枸邑县之义章村宿营，离枸邑县20里，走了95里。",
      "weather": "晴",
      "char_count": 52,
      "diary_id": "王恩茂日记",
      "diary_name": "《王恩茂日记》——红军长征到“七七“事变前夕",
      "diary_index": 1
    },
    {
      "date_raw": "1 月 8 日",
      "year": 1937,
      "month": 1,
      "day": 8,
      "text": "上午7时出发，经过土桥、千风园、通润镇，下午5时 半到达淳化县城内宿营，走了80里。",
      "weather": "晴",
      "char_count": 42,
      "diary_id": "王恩茂日记",
      "diary_name": "《王恩茂日记》——红军长征到“七七“事变前夕",
      "diary_index": 1
    },
    {
      "date_raw": "1 月 9 日",
      "year": 1937,
      "month": 1,
      "day": 9,
      "text": "上午7时出发，经过石桥镇、口头镇，下午3时半到达 泾阳县之桥底镇(石桥)宿营。\n\n1 月 1 0 日\n晴。\n在桥底镇休息。\n\n\n1 月 1 1 日\n晴 。\n上午6时出发，团以上干部经过云阳镇(方总驻地) 休息一小时，与二军团的干部同往岩屋前敌总政部开会，由博古同志报告西安事变的原因，党在西安事变中的 策略路线，西安事变后的形势，红军的任务。 下个本来还 有彭总指挥（彭德怀）报告，因各方面军的干部要回去，故未报 告。下午2时半经过云阳镇返回桥底镇。\n\n1 月 1 2 日\n晴。\n上午10时往泾阳县与县政府联络，下午1时到达泾 阳城，接见县长李性原，谈红军感谢泾阳民众慰劳红军的 敬意及红军目前的主张，并会见驻防城内之十七路军十 七师一零五团二营营副及西安派来泾阳训练保、甲之人 员。下午5时半返桥底镇政治部。\n\n\n1 月 1 3 日\n晴。\n上午9时率宣传部人员复往泾阳，进行扩大红军工作。",
      "weather": "晴",
      "char_count": 395,
      "diary_id": "王恩茂日记",
      "diary_name": "《王恩茂日记》——红军长征到“七七“事变前夕",
      "diary_index": 1
    },
    {
      "date_raw": "1月22日",
      "year": 1937,
      "month": 1,
      "day": 22,
      "text": "从13日起至22日上午，均在城内扩大红军。22日下 午2时转移扩红地区，从经阳城出发，到北杜镇因天晚 了，即在北杜镇宿营。\n\n1 月 2 3 日\n晴。\n上午6时半出发，经过马庄镇、店张驿，到兴平 县。\n\n1 月 2 4 日\n晴。\n在兴平县扩大红军，",
      "weather": "",
      "char_count": 124,
      "diary_id": "王恩茂日记",
      "diary_name": "《王恩茂日记》——红军长征到“七七“事变前夕",
      "diary_index": 1
    },
    {
      "date_raw": "1月25 日",
      "year": 1937,
      "month": 1,
      "day": 25,
      "text": "囚部队向东北地区转移集结待机，故我们扩红突击队亦须归返建制，往石桥镇归队。上午6时半出发，下午4 时许到达桥底镇。\n\n1 月 2 6 日\n晴 。\n上午7时出发，经过云阳镇、鲁桥镇，到达鲁底宿营。\n\n\n1 月 2 7 日\n晴。\n上午7时出发，下午2时许到达庄里镇(距富 平、耀县各30里。\n\n1 月 2 8 日\n晴。\n在庄里镇休息。下午6时开干部会议，张主任报告在 庄里镇的工作任务。\n\n\n1 月 2 9 日\n晴。\n仍在主里镇休息。下个6时开排长以上的积极分子 会议，王政委报告目前形势与我们的任务。\n\n1 月 3 0 日\n晴。\n仍在庄里镇休息。\n\n\n1 月 3 1 日\n阴。\n供给部有人去西安买东西，我参加去买各神革命书 籍。上午7时半往花朱家方总供给部，因方总供给部明日 才派人去西安，故在方总供给部等他们一天。",
      "weather": "晴",
      "char_count": 357,
      "diary_id": "王恩茂日记",
      "diary_name": "《王恩茂日记》——红军长征到“七七“事变前夕",
      "diary_index": 1
    },
    {
      "date_raw": "2 月 1 日",
      "year": 1937,
      "month": 2,
      "day": 1,
      "text": "上午7时动身，经过富平，到瓦窑头搭汽车到三原 县。",
      "weather": "晴",
      "char_count": 25,
      "diary_id": "王恩茂日记",
      "diary_name": "《王恩茂日记》——红军长征到“七七“事变前夕",
      "diary_index": 1
    },
    {
      "date_raw": "2 月 2 日",
      "year": 1937,
      "month": 2,
      "day": 2,
      "text": "上个8时，由三原坐汽车，因同路汽车过多(十五六 辆)沿途体息多次，12时许抵西安城，宿于西安北大街新 亚旅社，",
      "weather": "晴",
      "char_count": 55,
      "diary_id": "王恩茂日记",
      "diary_name": "《王恩茂日记》——红军长征到“七七“事变前夕",
      "diary_index": 1
    },
    {
      "date_raw": "2 月 3 日",
      "year": 1937,
      "month": 2,
      "day": 3,
      "text": "在西安购买各种革命书籍，正在南院街普育书局买 书时，忽街上人马乱跑，商店关门，风声紧张，我不知什么 事发，只好在书局停留，等候一小时，街道平静，始知发谣 风也。晚则宿东大街370号成记军服店。",
      "weather": "晴",
      "char_count": 96,
      "diary_id": "王恩茂日记",
      "diary_name": "《王恩茂日记》——红军长征到“七七“事变前夕",
      "diary_index": 1
    },
    {
      "date_raw": "2 月 4 日",
      "year": 1937,
      "month": 2,
      "day": 4,
      "text": "仍在西安，继续往各书局买书，并去西北饭店晋谒刘 秉林、胡希仲等先生，为他们留吃早餐。下午3时，胡希仲 先生又请我们吃晚饭。",
      "weather": "晴",
      "char_count": 61,
      "diary_id": "王恩茂日记",
      "diary_name": "《王恩茂日记》——红军长征到“七七“事变前夕",
      "diary_index": 1
    },
    {
      "date_raw": "2 月 5 日",
      "year": 1937,
      "month": 2,
      "day": 5,
      "text": "因西安事变和平解决，我们即回来。上午7时乘汽车，经咸阳、泾阳，因十七路军过泾河没有过完，等了 三四小时才渡径水。下午5时半到云阳镇前故总供给部。",
      "weather": "晴",
      "char_count": 72,
      "diary_id": "王恩茂日记",
      "diary_name": "《王恩茂日记》——红军长征到“七七“事变前夕",
      "diary_index": 1
    },
    {
      "date_raw": "2 月 6 日",
      "year": 1937,
      "month": 2,
      "day": 6,
      "text": "出云阳镇动身，经过鲁桥镇，到东沟(离鲁底  三 里 ) 宿 营 。",
      "weather": "晴",
      "char_count": 33,
      "diary_id": "王恩茂日记",
      "diary_name": "《王恩茂日记》——红军长征到“七七“事变前夕",
      "diary_index": 1
    },
    {
      "date_raw": "2 月 7 日",
      "year": 1937,
      "month": 2,
      "day": 7,
      "text": "由东沟出发，经过许多地方寨子，民众都武装起来，  守住寨子，并关门。我们走近去，他们才打开门。这种戒备  情况，我们到了蛋林才知道是防范东北军。他们说：“东北军在蒲城抢了老百姓许多东西，并收缴了蒲城民团武   装，现东北军二师驻在富平，距此20里，故不得不防范。” 等等。我们即向北走了，下午4时抵庄里镇。",
      "weather": "阴",
      "char_count": 153,
      "diary_id": "王恩茂日记",
      "diary_name": "《王恩茂日记》——红军长征到“七七“事变前夕",
      "diary_index": 1
    },
    {
      "date_raw": "2 月 8 日",
      "year": 1937,
      "month": 2,
      "day": 8,
      "text": "因为六军团已向东北曹村镇转移了，我们即向东化 走，下午3时半到达曹村镇田家寨子军团政治部，\n\n2 月 2 2 日\n\n从9日起至22 日，均在曹村镇。\n\n2 月 2 3 日\n\n阴。\n政治部决定：从2月25 日起至3月7日止，10天扩 大红军300 人：曹村50人，庄里150人，耀县100人，并增 加人到耀县与庄里镇去扩红，我亦参加，与张部长（张启龙）路到庄里镇。\n\n2 月 2 4 日\n\n晴。\n由庄里镇到耀县，下午参加耀县宣传队会议。\n\n\n2 月 2 5 日\n\n晴。\n参加耀县全县军民大会，大会主持者为十七路军独 立旅政治处，参加民众及民众武装和城内驻军达三万余 人。会场人挤人塞，群众抬人装的故事,化装高足队， 踊跃到会，热闹异常。晚上因这天是旧历元宵，龙灯、狮子 闹个不停，10年来未见之IE社会风俗，今日重见之矣。\n\n2 月 2 6 日\n\n晴。\n仍在耀县。我们的新剧团到耀县演新剧，博得军民鼓 掌称赞。\n\n\n2 月 2 7 日\n\n晴。\n仍在耀县。抗日宣传队开会：检查工作，并分配地区 进行扩红。\n\n2 月 2 8 日\n\n晴。\n仍在耀县。",
      "weather": "阴",
      "char_count": 471,
      "diary_id": "王恩茂日记",
      "diary_name": "《王恩茂日记》——红军长征到“七七“事变前夕",
      "diary_index": 1
    },
    {
      "date_raw": "3 月 1 日",
      "year": 1937,
      "month": 3,
      "day": 1,
      "text": "往西仁乡检查抗日宣传队工作，并到阿姑社。",
      "weather": "晴",
      "char_count": 20,
      "diary_id": "王恩茂日记",
      "diary_name": "《王恩茂日记》——红军长征到“七七“事变前夕",
      "diary_index": 1
    },
    {
      "date_raw": "3 月 2 日",
      "year": 1937,
      "month": 3,
      "day": 2,
      "text": "由西仁乡返耀县，闻讯红军3月1日起改名国民革命 军。",
      "weather": "晴",
      "char_count": 26,
      "diary_id": "王恩茂日记",
      "diary_name": "《王恩茂日记》——红军长征到“七七“事变前夕",
      "diary_index": 1
    },
    {
      "date_raw": "3 月 3 日",
      "year": 1937,
      "month": 3,
      "day": 3,
      "text": "由耀县返政治部，在庄里镇歇了一夜。地方部长李国 华同志与我谈庄里扩红工作等。",
      "weather": "晴",
      "char_count": 38,
      "diary_id": "王恩茂日记",
      "diary_name": "《王恩茂日记》——红军长征到“七七“事变前夕",
      "diary_index": 1
    },
    {
      "date_raw": "3 月 4 日",
      "year": 1937,
      "month": 3,
      "day": 4,
      "text": "由庄里镇返曹村镇政治部，向王政委、张主任简要汇 报耀县、庄里镇扩红工作。",
      "weather": "晴",
      "char_count": 36,
      "diary_id": "王恩茂日记",
      "diary_name": "《王恩茂日记》——红军长征到“七七“事变前夕",
      "diary_index": 1
    },
    {
      "date_raw": "3 月 5 日",
      "year": 1937,
      "month": 3,
      "day": 5,
      "text": "在曹村镇。我的右脚开始痛起米了，下午睡在床上己 经不能动了，医生给我上药时说：“这是关节炎。”",
      "weather": "阴",
      "char_count": 47,
      "diary_id": "王恩茂日记",
      "diary_name": "《王恩茂日记》——红军长征到“七七“事变前夕",
      "diary_index": 1
    },
    {
      "date_raw": "3 月 6 日",
      "year": 1937,
      "month": 3,
      "day": 6,
      "text": "脚仍痛，并膝盖发肿发热，伸曲痛苦难堪，晚上痛得 睡不安。",
      "weather": "晴",
      "char_count": 28,
      "diary_id": "王恩茂日记",
      "diary_name": "《王恩茂日记》——红军长征到“七七“事变前夕",
      "diary_index": 1
    },
    {
      "date_raw": "3 月 7 日",
      "year": 1937,
      "month": 3,
      "day": 7,
      "text": "脚仍痛，不能行动，解大、小便，都要人背。睡在床上过了一天。",
      "weather": "晴",
      "char_count": 29,
      "diary_id": "王恩茂日记",
      "diary_name": "《王恩茂日记》——红军长征到“七七“事变前夕",
      "diary_index": 1
    },
    {
      "date_raw": "3 月 8 日",
      "year": 1937,
      "month": 3,
      "day": 8,
      "text": "脚同样的痛，睡在床上过日子。",
      "weather": "晴",
      "char_count": 14,
      "diary_id": "王恩茂日记",
      "diary_name": "《王恩茂日记》——红军长征到“七七“事变前夕",
      "diary_index": 1
    },
    {
      "date_raw": "3 月 9 日",
      "year": 1937,
      "month": 3,
      "day": 9,
      "text": "右脚痛稍止，但左脚又痛起来了。\n\n\n3 月 1 0 日\n阴。\n左脚痛得特别厉害，夜晚睡觉都痛得喊“哎哟”哩!\n\n3 月 1 1 日\n晴。\n右脚痛差不多全部好了，可以自由转动，而左脚仍然 痛 ：\n\n3 月 1 2 日\n晴。\n左脚开始停痛，而不能转动自由则是一样的，如果左 脚和右脚一样那是可以行走，\n\n3 月 1 3 日\n阴。\n左脚比较好点，但还不能单独走路，需要扶着甚至背 着走路。有时人扶出来坐一下，稍稍离开铺榻。从5日下 个起到今日止，九天中只有12、13两日离开了一下铺榻， 在外面坐一坐，其余天天都睡在床上，真是不耐烦哩!同 时总是想着；我脚病的时候，还是病得好呢，如果病在行 军作战的时候，真是糟糕了，现在是和平局面的时候呢\n\n3 月 1 4 日\n阴。\n脚稍好，能慢慢地走，在休养着。\n\n\n3 月 1 5 日\n晴。\n到党大会筹备处，画画报，晚上才回来。\n\n\n3 月 1 6 日\n晴。\n到党大会筹备处写标语。\n\n\n3 月 1 7 日\n阴。\n王政委要我写红六军团突围远征会合一、四方面军 的经过。\n\n3 月 1 8 日\n\n阴 。\n参加党大会，王政委致开幕词，甘主任作政治报告。\n\n\n3 月 1 9 日\n阴 。\n参加党大会，张主任作支部工作总结报告，陈军长、 刘主任（刘道生）发言，王政委致闭幕词，\n\n3 月 2 0 日\n晴。\n写回曾涤同志的信。看了中共发言人的电文。\n\n\n3 月 2 1 日\n晴。\n编剧：《车夫》,并看新华社关丁二中全会的评论 及关丁托洛斯基派。\n\n3 月 2 2 日\n晴。\n看《列宁主义概论》第八章：党。下午上乙组政治课。 晚上抄写“长征简叙”。\n\n\n3 月 2 3 日\n阴 。\n早晨仍抄写“长征简叙”。下午听课，内容为社会进化\n简述：(一)原始社会；(二)族长宗法社会；(三)封建社会； (四)城市手工业制度，进到手工业工厂制度、商业资本社  会；(五)资本主义社会其特点：①商品经济；②垄断生产；\n③雇佣劳动。\n\n\n3 月 2 4 日\n阴。\n到补充团，清查老、弱、小孩共六十几个，都不合格， 不能当红军，介绍回家去。晚上写《奋斗报》上的“写在前  面”。\n\n3 月 2 5 日\n阴。\n上午看《政治常识》之“资本主义”段落。下午听课：\n“什么叫作价值、价值与价格、剩余价值、资本”。晚上听广 播，为南京开政治讨论会，题日“知难行易”。",
      "weather": "阴",
      "char_count": 980,
      "diary_id": "王恩茂日记",
      "diary_name": "《王恩茂日记》——红军长征到“七七“事变前夕",
      "diary_index": 1
    },
    {
      "date_raw": "7 月 1 日",
      "year": 1937,
      "month": 7,
      "day": 1,
      "text": "阴，下午雨。星期四。驻军，流曲镇。\n蒲城中学的学生参观团今大回去。他们本来是要到 庄里与延安去参观的，因为环境关系没有去。他们觉得红 军是伟大的。他们参观了我们的部队以后，就同我们说：“你们同老百姓的关系确实好得很，你们战士的学习热情 真是很高，没有笔墨纸砚写字，便在沙盘里写字”等。\n到训练班上课，讲毛主席的报告。\n政治部开会，首先朱明〔2 同志报告他来的任务是检 查支部工作与鉴定干部；次则刘副主任（刘道生）传达方政关于 5、6月政治教育总结的精神以及7、8、9月政治教育计划： 提出我们首先定出7月份的教育计划：甲组7月前两个星 期教完毛主席的报告，以后教中国怎样降到半殖民 地;乙组教完帝国主义前五课；丙组教完抗日军人读 本前五课。以后，罗副主任（罗志敏）发言，王政委即作结论。\n\n7月 ·2 日\n雨。星期五。驻军，流曲镇。\n到训练班上课，继续讲毛主席的报告。\n看书：《大众哲学》。看了“哲学的踪迹可以在口常生 活里找到”、“哲学与日常生活感想”(哲学是更有系统的， 日常感想是混杂的)、“哲学神秘的原因 ”— 只看到日常感想与哲学的差别与对立而没有看到口常感想与哲学的共同与统一的地方以及哲学观念论等，“临到共同一件 事，各人的感想不同”、“各种感想代表各种哲学”、“哲学是人们对丁世界根本的认识与态度”、“哲学上的认识和 态度是最普遍最一般的”等。\n晚上看《解放》报第6期。",
      "weather": "",
      "char_count": 593,
      "diary_id": "王恩茂日记",
      "diary_name": "《王恩茂日记》——红军长征到“七七“事变前夕",
      "diary_index": 1
    },
    {
      "date_raw": "7 月 3 日",
      "year": 1937,
      "month": 7,
      "day": 3,
      "text": "晴。星期六。驻军，流曲镇。\n检查家信。有许多红属鼓励红军努力抗日救国，如： “昌林爱儿知悉，你写给我的信己经收到，你说抗日救国， 我非常同情，因为‘九一八事变23 以来，国耻的影子永 沉在我的脑海里不能忘记，可是你的父亲身当暮年不能  来参加，望你把毕生的热血，洒在抗日战线上，就算你报  答我15年来抚育你的恩了。再则我的生活有你哥哥负 责，你不要关心，努力干你的抗日工作。有暇时可写信给  你父亲。你的父亲龙恩，旧历五月六日。”还有些家信说， 乡村的老百姓，都在庆祝你们胜利，希望你们早日赶走日  本。\n作了一点笔记，记的是中国怎样降到半殖民地，原因 是：(1)由于资本帝国主义的进攻；(2)由于清廷〔1〕十足 的封建政府，以至袁世凯52〕到现在的政府，没有执行过  正确的国策，官僚军阀的卖国误国；(3)镇压了民众的反  帝斗争。中国为什么还没有沦为完全的殖民地，原因是：\n(1)中国民众反帝力量的伟大；(2)苏联社会主义的胜利， 全世界无产阶级和殖民地、半殖民地民族反对帝国主义 侵略；(3)帝国主义相互间的矛盾加深。",
      "weather": "",
      "char_count": 463,
      "diary_id": "王恩茂日记",
      "diary_name": "《王恩茂日记》——红军长征到“七七“事变前夕",
      "diary_index": 1
    },
    {
      "date_raw": "7 月 4 日",
      "year": 1937,
      "month": 7,
      "day": 4,
      "text": "晴。星期日。驻军，流曲镇。\n今天是星期日，训练班进行测验，我拟好了五个题 目，本来我自己去测验，因有事未去。\n看了一些方政来的文件和报章。\n整个上午(早饭后)与下午2时抄写王政委著作之六 军团小史。\n晚饭后，本米各团进行篮球竞赛，因开晚会，故去参 加晚会，没有进行篮球比赛。晚会内容： 一个是王政委的报告，一个是陈军长的报告。离开红六军团将近两月的王 政委，今天与全体指战员见面，他开头就说：我因参加苏 区党大会,好久没有同你们讲话，今天说的是苏区党 大会的精神以及苏区党大会后的形势与党的任务等，陈 军长报告5、6月红六军团的进步，继续这种进步，努力完 成彭总指挥给予我们创造红六军团为二方面军的模范军 团的光荣任务。\n晚上王政委要我写信，他告诉我写信的内容。",
      "weather": "",
      "char_count": 331,
      "diary_id": "王恩茂日记",
      "diary_name": "《王恩茂日记》——红军长征到“七七“事变前夕",
      "diary_index": 1
    },
    {
      "date_raw": "7 月 5 日",
      "year": 1937,
      "month": 7,
      "day": 5,
      "text": "晴。星期一。驻军，流曲镇。\n到训练班上了两点钟的课，上的是毛主席报告的第 三部分：“我们的领导责任”之第一点“中国反帝反封建的 资产阶级民主革命的任务， ……必须经过无产阶级的领 导，才能够完成。”\n按照昨天土政委说的写信的内容，写了两封家信，主 要是为了扩大党的主张的宣传。",
      "weather": "",
      "char_count": 138,
      "diary_id": "王恩茂日记",
      "diary_name": "《王恩茂日记》——红军长征到“七七“事变前夕",
      "diary_index": 1
    },
    {
      "date_raw": "7 月 6 日",
      "year": 1937,
      "month": 7,
      "day": 6,
      "text": "阴，下了一点雨。星期二。驻军，流曲镇。\n转发了工政委写来的 一个通知，内容是要各团特别 小组，讨论《解放》报4、5期上的斯大林的报告和结论，因 它对于我们同样有重大的意义。\n参加实弹射击，并兼带到五十二团看了一下，听了他 们上政治课，检查了他们战士的识字成绩，还是很差，如 一连六班战士张心成，是在毕节参加红军的，现在还只识 得十几个字，连工农兵学商几个字都识不到。同时看见二 拌的房子里一个老百姓在那里写字，写着反帝反封建的 斗争等字。我以为他是新战士，问他你当红军好久?他说 是老百姓。我问，老百姓为什么在这里写字呢?他说要努 力学习哩!这里可以看到部队的学习热情不仅反映在战 士中，而且已经传播到群众中去了。\n晚上继续为王政委写完一封信。",
      "weather": "",
      "char_count": 322,
      "diary_id": "王恩茂日记",
      "diary_name": "《王恩茂日记》——红军长征到“七七“事变前夕",
      "diary_index": 1
    }
  ],
  "entry_count": 139
}